Workbook
Name Discount_Rate: 'Integrated DCF Model'!$E$10
Name Discount_Rate: #REF!
Name IQ_CH: 110000
Name IQ_CQ: 5000
Name IQ_CY: 10000
Name IQ_DAILY: 500000
Name IQ_FH: 100000
Name IQ_FQ: 500
Name IQ_FWD_CY: 10001
Name IQ_FWD_CY1: 10002
Name IQ_FWD_CY2: 10003
Name IQ_FWD_FY: 1001
Name IQ_FWD_FY1: 1002
Name IQ_FWD_FY2: 1003
Name IQ_FWD_Q: 501
Name IQ_FWD_Q1: 502
Name IQ_FWD_Q2: 503
Name IQ_FY: 1000
Name IQ_LATESTK: 1000
Name IQ_LATESTQ: 500
Name IQ_LTM: 2000
Name IQ_LTMMONTH: 120000
Name IQ_MONTH: 15000
Name IQ_NTM: 6000
Name IQ_TODAY: 0
Name IQ_WEEK: 50000
Name IQ_YTD: 3000
Name IQ_YTDMONTH: 130000
Name Tax: [1]DCF!$D$44

Sheet Revenue Build & Growth Drivers
C2: ="Revenue Build & Growth Drivers For "&D5 -> Revenue Build & Growth Drivers For Keysight Technologies, Inc.
C3: $ in thousands except per unit
C5: Company Name | D5: Keysight Technologies, Inc.
C6: Ticker | D6: KEYS
C7: Valuation Date | D7: 45394
C8: Latest Adj. Closing Share Price Date | D8: 45393
C9: Latest Adj. Closing Share Price | D9: 160.14
C11: Revenue Projection | D11: Historical | G11: Projected
D12: ='Financial Statement Model'!D12 -> 44500 | E12: ='Financial Statement Model'!E12 -> 44865 | F12: ='Financial Statement Model'!F12 -> 45230 | G12: ='Financial Statement Model'!G12 -> 45596 | H12: ='Financial Statement Model'!H12 -> 45961 | I12: ='Financial Statement Model'!I12 -> 46326 | J12: ='Financial Statement Model'!J12 -> 46691 | K12: ='Financial Statement Model'!K12 -> 47057
C14: Total Revenues | D14: =+D23+D30 -> 4941000 | E14: =+E23+E30 -> 5420000 | F14: =+F23+F30 -> 5464000 | G14: =+G23+G30 -> 5740940 | H14: =+H23+H30 -> 6106477.8 | I14: =+I23+I30 -> 6500932.8 | J14: =+J23+J30 -> 6896456.2 | K14: =+K23+K30 -> 7322384.8
C15: % growth | E15: =+E14/D14-1 -> 0.096943938 | F15: =+F14/E14-1 -> 0.0081180812 | G15: =+G14/F14-1 -> 0.05068448 | H15: =+H14/G14-1 -> 0.063672116 | I15: =+I14/H14-1 -> 0.064596162 | J15: =+J14/I14-1 -> 0.060841011 | K15: =+K14/J14-1 -> 0.061760511
C17: Segmental Revenue Schedule | D17: Historical | G17: Projected
D18: ='Financial Statement Model'!D12 -> 44500 | E18: ='Financial Statement Model'!E12 -> 44865 | F18: ='Financial Statement Model'!F12 -> 45230 | G18: ='Financial Statement Model'!G12 -> 45596 | H18: ='Financial Statement Model'!H12 -> 45961 | I18: ='Financial Statement Model'!I12 -> 46326 | J18: ='Financial Statement Model'!J12 -> 46691 | K18: ='Financial Statement Model'!K12 -> 47057
C20: Communications Solutions Group (CSG)
C21: Aerospace, Defense & Government | D21: 1142000 | E21: 1171000 | F21: 1250000 | G21: =+F21*(1+G38) -> 1331250 | H21: =+G21*(1+H38) -> 1411125 | I21: =+H21*(1+I38) -> 1509903.8 | J21: =+I21*(1+J38) -> 1585398.9 | K21: =+J21*(1+K38) -> 1664668.9
C22: Commercial Communications | D22: 2381000 | E22: 2632000 | F22: 2435000 | G22: =+F22*(1+G39) -> 2435000 | H22: =+G22*(1+H39) -> 2483700 | I22: =+H22*(1+I39) -> 2558211 | J22: =+I22*(1+J39) -> 2634957.3 | K22: =+J22*(1+K39) -> 2714006
C23: Total CSG Revenue | D23: =SUM(D21:D22) -> 3523000 | E23: =SUM(E21:E22) -> 3803000 | F23: =SUM(F21:F22) -> 3685000 | G23: =SUM(G21:G22) -> 3766250 | H23: =SUM(H21:H22) -> 3894825 | I23: =SUM(I21:I22) -> 4068114.8 | J23: =SUM(J21:J22) -> 4220356.3 | K23: =SUM(K21:K22) -> 4378674.9
C24: % growth | E24: =+E23/D23-1 -> 0.079477718 | F24: =+F23/E23-1 -> -0.031028136 | G24: =+G23/F23-1 -> 0.022048847 | H24: =+H23/G23-1 -> 0.034138732 | I24: =+I23/H23-1 -> 0.044492307 | J24: =+J23/I23-1 -> 0.037423113 | K24: =+K23/J23-1 -> 0.037513105
C26: % of CSG Revenue
C27: =C21 -> Aerospace, Defense & Government | D27: =+D21/D$23 -> 0.32415555 | E27: =+E21/E$23 -> 0.3079148 | F27: =+F21/F$23 -> 0.33921303 | G27: =+G21/G$23 -> 0.3534683 | H27: =+H21/H$23 -> 0.36230768 | I27: =+I21/I$23 -> 0.37115564 | J27: =+J21/J$23 -> 0.37565524 | K27: =+K21/K$23 -> 0.3801764
C28: =C22 -> Commercial Communications | D28: =+D22/D$23 -> 0.67584445 | E28: =+E22/E$23 -> 0.6920852 | F28: =+F22/F$23 -> 0.66078697 | G28: =+G22/G$23 -> 0.6465317 | H28: =+H22/H$23 -> 0.63769232 | I28: =+I22/I$23 -> 0.62884436 | J28: =+J22/J$23 -> 0.62434476 | K28: =+K22/K$23 -> 0.6198236
C30: Electronic Industrial Solutions Group (EISG) | D30: 1418000 | E30: 1617000 | F30: 1779000 | G30: =+F30*(1+G40) -> 1974690 | H30: =+G30*(1+H40) -> 2211652.8 | I30: =+H30*(1+I40) -> 2432818.1 | J30: =+I30*(1+J40) -> 2676099.9 | K30: =+J30*(1+K40) -> 2943709.9
C31: % growth | E31: =+E30/D30-1 -> 0.1403385 | F31: =+F30/E30-1 -> 0.10018553 | G31: =+G30/F30-1 -> 0.11 | H31: =+H30/G30-1 -> 0.12 | I31: =+I30/H30-1 -> 0.1 | J31: =+J30/I30-1 -> 0.1 | K31: =+K30/J30-1 -> 0.1
C33: Growth Driver Assumptions
C35: Segment Revenue Growth Drivers | D35: Historical | G35: Projected
D36: ='Financial Statement Model'!D12 -> 44500 | E36: ='Financial Statement Model'!E12 -> 44865 | F36: ='Financial Statement Model'!F12 -> 45230 | G36: ='Financial Statement Model'!G12 -> 45596 | H36: ='Financial Statement Model'!H12 -> 45961 | I36: ='Financial Statement Model'!I12 -> 46326 | J36: ='Financial Statement Model'!J12 -> 46691 | K36: ='Financial Statement Model'!K12 -> 47057
C37: Revenue Growth Rate by Segment
C38: =+C21 -> Aerospace, Defense & Government | E38: =+E21/D21-1 -> 0.025394046 | F38: =+F21/E21-1 -> 0.067463706 | G38: 0.065 | H38: 0.06 | I38: 0.07 | J38: 0.05 | K38: 0.05
C39: =+C22 -> Commercial Communications | E39: =+E22/D22-1 -> 0.10541789 | F39: =+F22/E22-1 -> -0.074848024 | G39: 0 | H39: 0.02 | I39: 0.03 | J39: 0.03 | K39: 0.03
C40: =C30 -> Electronic Industrial Solutions Group (EISG) | E40: =+E30/D30-1 -> 0.1403385 | F40: =+F30/E30-1 -> 0.10018553 | G40: 0.11 | H40: 0.12 | I40: 0.1 | J40: 0.1 | K40: 0.1
C42: General Growth Drivers | D42: Historical | G42: Projected
D43: ='Financial Statement Model'!D12 -> 44500 | E43: ='Financial Statement Model'!E12 -> 44865 | F43: ='Financial Statement Model'!F12 -> 45230 | G43: ='Financial Statement Model'!G12 -> 45596 | H43: ='Financial Statement Model'!H12 -> 45961 | I43: ='Financial Statement Model'!I12 -> 46326 | J43: ='Financial Statement Model'!J12 -> 46691 | K43: ='Financial Statement Model'!K12 -> 47057
C44: Operating Expenses
C45: Gross Profit Margin | D45: ='Financial Statement Model'!D35 -> 0.62092694 | E45: ='Financial Statement Model'!E35 -> 0.63376384 | F45: ='Financial Statement Model'!F35 -> 0.64403367 | G45: 0.65 | H45: 0.65 | I45: 0.65 | J45: 0.65 | K45: 0.65
C46: SG&A % Revenue | D46: ='Financial Statement Model'!D36 -> 0.40214531 | E46: ='Financial Statement Model'!E36 -> 0.38726937 | F46: ='Financial Statement Model'!F36 -> 0.38854319 | G46: 0.38 | H46: 0.38 | I46: 0.38 | J46: 0.38 | K46: 0.38
C47: Other Operating Expense % of Revenue | D47: ='Financial Statement Model'!D37 -> 0 | E47: ='Financial Statement Model'!E37 -> 0 | F47: ='Financial Statement Model'!F37 -> 0 | G47: 0 | H47: 0 | I47: 0 | J47: 0 | K47: 0
C48: Days Sales Outstanding | D48: ='Financial Statement Model'!D118 -> 54.295689 | E48: ='Financial Statement Model'!E118 -> 60.945572 | F48: ='Financial Statement Model'!F118 -> 60.120791 | G48: 60 | H48: 60 | I48: 60 | J48: 60 | K48: 60
C49: Inventory Turnover | E49: ='Financial Statement Model'!E129 -> 1.8779565 | F49: ='Financial Statement Model'!F129 -> 1.6276151 | G49: 1.5 | H49: 1.5 | I49: 1.5 | J49: 1.5 | K49: 1.5

Sheet Financial Statement Model
C2: ="Financial Statement Model For "&D5 -> Financial Statement Model For Keysight Technologies, Inc.
C3: $ in thousands except per share
C5: Company Name | D5: ='Revenue Build & Growth Drivers'!D5 -> Keysight Technologies, Inc. | G5: Circ toggle (1=on, 0=off) | J5: 1
C6: Ticker | D6: ='Revenue Build & Growth Drivers'!D6 -> KEYS
C7: Valuation Date | D7: ='Revenue Build & Growth Drivers'!D7 -> 45394
C8: Latest Adj. Closing Share Price Date | D8: ='Revenue Build & Growth Drivers'!D8 -> 45393
C9: Latest Adj. Closing Share Price | D9: ='Revenue Build & Growth Drivers'!D9 -> 160.14
C11: Income Statement | D11: Historical | G11: Projected | M11: 5 Year
D12: 44500 | E12: =EOMONTH(D12,12) -> 44865 | F12: =EOMONTH(E12,12) -> 45230 | G12: =EOMONTH(F12,12) -> 45596 | H12: =EOMONTH(G12,12) -> 45961 | I12: =EOMONTH(H12,12) -> 46326 | J12: =EOMONTH(I12,12) -> 46691 | K12: =EOMONTH(J12,12) -> 47057 | M12: CAGR
C14: Total Revenues | D14: 4941000 | E14: 5420000 | F14: 5464000 | G14: =+F14*(1+G34) -> 5740940 | H14: =+G14*(1+H34) -> 6106477.8 | I14: =+H14*(1+I34) -> 6500932.8 | J14: =+I14*(1+J34) -> 6896456.2 | K14: =+J14*(1+K34) -> 7322384.8 | M14: =+_xlfn.RRI(YEAR($K$12)-YEAR($F$12),F14,K14) -> 0.060299048
C15: Less: Cost of Sales | D15: 1873000 | E15: 1985000 | F15: 1945000 | G15: =+G14-G16 -> 2009329 | H15: =+H14-H16 -> 2137267.2 | I15: =+I14-I16 -> 2275326.5 | J15: =+J14-J16 -> 2413759.7 | K15: =+K14-K16 -> 2562834.7
C16: Gross Profit | D16: 3068000 | E16: 3435000 | F16: 3519000 | G16: =+G14*G35 -> 3731611 | H16: =+H14*H35 -> 3969210.6 | I16: =+I14*I35 -> 4225606.3 | J16: =+J14*J35 -> 4482696.5 | K16: =+K14*K35 -> 4759550.1 | M16: =+_xlfn.RRI(YEAR($K$12)-YEAR($F$12),F16,K16) -> 0.06225633
C17: SG&A Expense | D17: 1987000 | E17: 2099000 | F17: 2123000 | G17: =+G14*G36 -> 2181557.2 | H17: =+H14*H36 -> 2320461.6 | I17: =+I14*I36 -> 2470354.5 | J17: =+J14*J36 -> 2620653.3 | K17: =+K14*K36 -> 2782506.2
C18: Other Operating Expense | D18: 0 | E18: 0 | F18: 0 | G18: =+G37*G14 -> 0 | H18: =+H37*H14 -> 0 | I18: =+I37*I14 -> 0 | J18: =+J37*J14 -> 0 | K18: =+K37*K14 -> 0
C19: Operating Profit (EBIT) | D19: 1081000 | E19: 1336000 | F19: 1396000 | G19: =+G16-G17-G18 -> 1550053.8 | H19: =+H16-H17-H18 -> 1648749 | I19: =+I16-I17-I18 -> 1755251.9 | J19: =+J16-J17-J18 -> 1862043.2 | K19: =+K16-K17-K18 -> 1977043.9 | M19: =+_xlfn.RRI(YEAR($K$12)-YEAR($F$12),F19,K19) -> 0.072077494
C20: Nonoperating Income | D20: 27000 | E20: 62000 | F20: 143000 | G20: =G209 -> 127206.63 | H20: =H209 -> 172659.53 | I20: =I209 -> 236415.18 | J20: =J209 -> 291052.44 | K20: =K209 -> 351538.12
C21: Interest Expense | D21: 79000 | E21: 79000 | F21: 78000 | G21: =G204 -> 65859.353 | H21: =H204 -> 52833.984 | I21: =I204 -> 51971.006 | J21: =J204 -> 36792.863 | K21: =K204 -> 21614.72
C22: Unusual Expenses | D22: 19000 | E22: 34000 | F22: 104000 | G22: 0 | H22: 0 | I22: 0 | J22: 0 | K22: 0
C23: Pre-tax Profit | D23: 1010000 | E23: 1285000 | F23: 1357000 | G23: =+G19+G20-G21-G22 -> 1611401.1 | H23: =+H19+H20-H21-H22 -> 1768574.6 | I23: =+I19+I20-I21-I22 -> 1939696 | J23: =+J19+J20-J21-J22 -> 2116302.7 | K23: =+K19+K20-K21-K22 -> 2306967.3 | M23: =+_xlfn.RRI(YEAR($K$12)-YEAR($F$12),F23,K23) -> 0.11196807
C24: Income Taxes | D24: 116000 | E24: 161000 | F24: 300000 | G24: =+G23*G41 -> 356241.95 | H24: =+H23*H41 -> 390989.22 | I24: =+I23*I41 -> 428820.05 | J24: =+J23*J41 -> 467863.54 | K24: =+K23*K41 -> 510014.88
C25: Minority interest | D25: 0 | E25: 0 | F25: 0 | G25: =G175 -> 0 | H25: =H175 -> 0 | I25: =I175 -> 0 | J25: =J175 -> 0 | K25: =K175 -> 0
C26: Net Income | D26: 894000 | E26: 1124000 | F26: 1057000 | G26: =+G23-G24-G25 -> 1255159.1 | H26: =+H23-H24-H25 -> 1377585.3 | I26: =+I23-I24-I25 -> 1510876 | J26: =+J23-J24-J25 -> 1648439.2 | K26: =+K23-K24-K25 -> 1796952.4 | M26: =+_xlfn.RRI(YEAR($K$12)-YEAR($F$12),F26,K26) -> 0.11196807
C28: Depreciation and Amortization | D28: 291000 | E28: 220000 | F28: 210000 | G28: =+G155+G146 -> 173968.09 | H28: =+H155+H146 -> 162626.93 | I28: =+I155+I146 -> 160426.57 | J28: =+J155+J146 -> 162432.29 | K28: =+K155+K146 -> 167508.9
C29: EBITDA | D29: 1372000 | E29: 1556000 | F29: 1606000 | G29: =+G19+G28 -> 1724021.9 | H29: =+H19+H28 -> 1811375.9 | I29: =+I19+I28 -> 1915678.4 | J29: =+J19+J28 -> 2024475.4 | K29: =+K19+K28 -> 2144552.8 | M29: =+_xlfn.RRI(YEAR($K$12)-YEAR($F$12),F29,K29) -> 0.059542156
C31: Stock Compensation and Exercise of Options | D31: 103000 | E31: 125000 | F31: 135000 | G31: =+AVERAGE(D31:F31) -> 121000 | H31: =+AVERAGE(E31:G31) -> 127000 | I31: =+AVERAGE(F31:H31) -> 127666.67 | J31: =+AVERAGE(G31:I31) -> 125222.22 | K31: =+AVERAGE(H31:J31) -> 126629.63
C33: Growth Rates and Margins
C34: Revenue Growth | E34: =+E14/D14-1 -> 0.096943938 | F34: =+F14/E14-1 -> 0.0081180812 | G34: =+'Revenue Build & Growth Drivers'!G15 -> 0.05068448 | H34: =+'Revenue Build & Growth Drivers'!H15 -> 0.063672116 | I34: =+'Revenue Build & Growth Drivers'!I15 -> 0.064596162 | J34: =+'Revenue Build & Growth Drivers'!J15 -> 0.060841011 | K34: =+'Revenue Build & Growth Drivers'!K15 -> 0.061760511
C35: Gross Profit Margin | D35: =+D16/D14 -> 0.62092694 | E35: =+E16/E14 -> 0.63376384 | F35: =+F16/F14 -> 0.64403367 | G35: ='Revenue Build & Growth Drivers'!G45 -> 0.65 | H35: ='Revenue Build & Growth Drivers'!H45 -> 0.65 | I35: ='Revenue Build & Growth Drivers'!I45 -> 0.65 | J35: ='Revenue Build & Growth Drivers'!J45 -> 0.65 | K35: ='Revenue Build & Growth Drivers'!K45 -> 0.65
C36: SG&A % of Revenue | D36: =+D17/D14 -> 0.40214531 | E36: =+E17/E14 -> 0.38726937 | F36: =+F17/F14 -> 0.38854319 | G36: ='Revenue Build & Growth Drivers'!G46 -> 0.38 | H36: ='Revenue Build & Growth Drivers'!H46 -> 0.38 | I36: ='Revenue Build & Growth Drivers'!I46 -> 0.38 | J36: ='Revenue Build & Growth Drivers'!J46 -> 0.38 | K36: ='Revenue Build & Growth Drivers'!K46 -> 0.38
C37: Other Operating Expense % of Revenue | D37: =+D18/D14 -> 0 | E37: =+E18/E14 -> 0 | F37: =+F18/F14 -> 0 | G37: ='Revenue Build & Growth Drivers'!G47 -> 0 | H37: ='Revenue Build & Growth Drivers'!H47 -> 0 | I37: ='Revenue Build & Growth Drivers'!I47 -> 0 | J37: ='Revenue Build & Growth Drivers'!J47 -> 0 | K37: ='Revenue Build & Growth Drivers'!K47 -> 0
C38: EBIT Margin | D38: =+D19/D14 -> 0.21878162 | E38: =+E19/E14 -> 0.24649446 | F38: =+F19/F14 -> 0.25549048 | G38: =+G19/G14 -> 0.27 | H38: =+H19/H14 -> 0.27 | I38: =+I19/I14 -> 0.27 | J38: =+J19/J14 -> 0.27 | K38: =+K19/K14 -> 0.27
C39: EBITDA Margin | D39: =+D29/D14 -> 0.27767658 | E39: =+E29/E14 -> 0.28708487 | F39: =+F29/F14 -> 0.29392387 | G39: =+G29/G14 -> 0.30030307 | H39: =+H29/H14 -> 0.29663187 | I39: =+I29/I14 -> 0.29467747 | J39: =+J29/J14 -> 0.29355301 | K39: =+K29/K14 -> 0.29287628
C40: Profit Margin | D40: =+D26/D14 -> 0.18093503 | E40: =+E26/E14 -> 0.20738007 | F40: =+F26/F14 -> 0.19344802 | G40: =+G26/G14 -> 0.21863303 | H40: =+H26/H14 -> 0.2255941 | I40: =+I26/I14 -> 0.23240911 | J40: =+J26/J14 -> 0.239027 | K40: =+K26/K14 -> 0.24540535
C41: Effective Tax Rate | D41: =+D24/D23 -> 0.11485149 | E41: =+E24/E23 -> 0.12529183 | F41: =+F24/F23 -> 0.2210759 | G41: =+IF(F41<0,AVERAGEIFS(D41:F41,D41:F41,">0"),F41) -> 0.2210759 | H41: =+G41 -> 0.2210759 | I41: =+H41 -> 0.2210759 | J41: =+I41 -> 0.2210759 | K41: =+J41 -> 0.2210759
C43: Balance Sheet | D43: Historical | G43: Projected | M43: 5 Year
D44: =+D$12 -> 44500 | E44: =+E$12 -> 44865 | F44: =+F$12 -> 45230 | G44: =+G$12 -> 45596 | H44: =+H$12 -> 45961 | I44: =+I$12 -> 46326 | J44: =+J$12 -> 46691 | K44: =+K$12 -> 47057 | M44: CAGR
C46: Cash & Short-Term Investments | D46: 2052000 | E46: 2042000 | F46: 2472000 | G46: =+F46+G103 -> 3157517 | H46: =+G46+H103 -> 4483513.6 | I46: =+H46+I103 -> 5979017.1 | J46: =+I46+J103 -> 6901480.1 | K46: =+J46+K103 -> 8655805 | M46: =+_xlfn.RRI(YEAR($K$12)-YEAR($F$12),F46,K46) -> 0.28484814
C47: Short-Term Receivables | D47: 735000 | E47: 905000 | F47: 900000 | G47: =G113 -> 945616.03 | H47: =H113 -> 1005825.4 | I47: =I113 -> 1070797.9 | J47: =J113 -> 1135946.3 | K47: =K113 -> 1206102.9
C48: Inventories | D48: 777000 | E48: 1057000 | F48: 1195000 | G48: =G124 -> 1234523.5 | H48: =H124 -> 1313128.2 | I48: =I124 -> 1397951.2 | J48: =J124 -> 1483004 | K48: =K124 -> 1574595.1
C49: Other Current Assets | D49: 270000 | E49: 230000 | F49: 242000 | G49: =+F49*(1+G34) -> 254265.64 | H49: =+G49*(1+H34) -> 270455.28 | I49: =+H49*(1+I34) -> 287925.65 | J49: =+I49*(1+J34) -> 305443.34 | K49: =+J49*(1+K34) -> 324307.67
C50: Total Current Assets | D50: 3834000 | E50: 4234000 | F50: 4809000 | G50: =+SUM(G46:G49) -> 5591922.1 | H50: =+SUM(H46:H49) -> 7072922.5 | I50: =+SUM(I46:I49) -> 8735691.8 | J50: =+SUM(J46:J49) -> 9825873.7 | K50: =+SUM(K46:K49) -> 11760811
C51: Net Property, Plant & Equipment | D51: 877000 | E51: 910000 | F51: 987000 | G51: =+G156+G237 -> 1050103 | H51: =+H156+H237 -> 1121280.4 | I51: =+I156+I237 -> 1196725.5 | J51: =+J156+J237 -> 1276081.7 | K51: =+K156+K237 -> 1360436.3
C52: Total Long-Term Investments | D52: 134000 | E52: 210000 | F52: 97000 | G52: =+F52*(1+G$34) -> 101916.39 | H52: =+G52*(1+H$34) -> 108405.63 | I52: =+H52*(1+I$34) -> 115408.21 | J52: =+I52*(1+J$34) -> 122429.77 | K52: =+J52*(1+K$34) -> 129991.09
C53: Intangible Assets | D53: 1900000 | E53: 1771000 | F53: 1795000 | G53: =+G141+G147 -> 1742000 | H53: =+H141+H147 -> 1707000 | I53: =+I141+I147 -> 1683000 | J53: =+J141+J147 -> 1665000 | K53: =+K141+K147 -> 1651000
C54: Deferred Tax Assets | D54: 711000 | E54: 667000 | F54: 671000 | G54: =+F54*(1+G$34) -> 705009.29 | H54: =+G54*(1+H$34) -> 749898.72 | I54: =+H54*(1+I$34) -> 798339.3 | J54: =+I54*(1+J$34) -> 846911.07 | K54: =+J54*(1+K$34) -> 899216.73
C55: Other Assets | D55: 325000 | E55: 306000 | F55: 324000 | G55: =+F55*(1+G$34) -> 340421.77 | H55: =+G55*(1+H$34) -> 362097.15 | I55: =+H55*(1+I$34) -> 385487.23 | J55: =+I55*(1+J$34) -> 408940.67 | K55: =+J55*(1+K$34) -> 434197.05
C56: Total Assets | D56: 7781000 | E56: 8098000 | F56: 8683000 | G56: =+SUM(G50:G55) -> 9531372.6 | H56: =+SUM(H50:H55) -> 11121604 | I56: =+SUM(I50:I55) -> 12914652 | J56: =+SUM(J50:J55) -> 14145237 | K56: =+SUM(K50:K55) -> 16235652
C58: ST Debt & Curr. Portion LT Debt | D58: 41000 | E58: 39000 | F58: 639000 | G58: =+G192+G200+G229 -> 99559.19 | H58: =+H192+H200+H229 -> 44703.351 | I58: =+I192+I200+I229 -> 745591.02 | J58: =+J192+J200+J229 -> 50486.502 | K58: =+K192+K200+K229 -> 550604.57
C59: Accounts Payable | D59: 287000 | E59: 348000 | F59: 286000 | G59: =+F59*(1+(G15/F15-1)) -> 295459.17 | H59: =+G59*(1+(H15/G15-1)) -> 314271.69 | I59: =+H59*(1+(I15/H15-1)) -> 334572.43 | J59: =+I59*(1+(J15/I15-1)) -> 354928.15 | K59: =+J59*(1+(K15/J15-1)) -> 376848.7
C60: Income Tax Payable | D60: 74000 | E60: 96000 | F60: 90000 | G60: 0 | H60: 0 | I60: 0 | J60: 0 | K60: 0
C61: Other Current Liabilities | D61: 907000 | E61: 924000 | F61: 1034000 | G61: =+F61*(1+G34) -> 1086407.8 | H61: =+G61*(1+H34) -> 1155581.6 | I61: =+H61*(1+I34) -> 1230227.8 | J61: =+I61*(1+J34) -> 1305076.1 | K61: =+J61*(1+K34) -> 1385678.2
C62: Total Current Liabilities | D62: 1309000 | E62: 1407000 | F62: 2049000 | G62: =+SUM(G58:G61) -> 1481426.1 | H62: =+SUM(H58:H61) -> 1514556.7 | I62: =+SUM(I58:I61) -> 2310391.2 | J62: =+SUM(J58:J61) -> 1710490.7 | K62: =+SUM(K58:K61) -> 2313131.5
C64: Long-Term Debt | D64: 1982000 | E64: 1979000 | F64: 1387000 | G64: =+G201+G232 -> 1396731.4 | H64: =+H201+H232 -> 1409576.1 | I64: =+I201+I232 -> 725436.88 | J64: =+J201+J232 -> 739335.21 | K64: =+K201+K232 -> 257301.96
C65: Provision for Risks & Charges | D65: 180000 | E65: 70000 | F65: 78000 | G65: =+F65*(1+G34) -> 81953.389 | H65: =+G65*(1+H34) -> 87171.535 | I65: =+H65*(1+I34) -> 92802.482 | J65: =+I65*(1+J34) -> 98448.679 | K65: =+J65*(1+K34) -> 104528.92
C66: Deferred Tax Liabilities | D66: 0 | E66: 0 | F66: 0 | G66: =+F66*(1+G34) -> 0 | H66: =+G66*(1+H34) -> 0 | I66: =+H66*(1+I34) -> 0 | J66: =+I66*(1+J34) -> 0 | K66: =+J66*(1+K34) -> 0
C67: Other Liabilities | D67: 526000 | E67: 481000 | F67: 515000 | G67: =+F67*(1+G34) -> 541102.51 | H67: =+G67*(1+H34) -> 575555.65 | I67: =+H67*(1+I34) -> 612734.34 | J67: =+I67*(1+J34) -> 650013.71 | K67: =+J67*(1+K34) -> 690158.89
C68: Total Liabilities | D68: 3997000 | E68: 3937000 | F68: 4029000 | G68: =+SUM(G64:G67,G62) -> 3501213.4 | H68: =+SUM(H64:H67,H62) -> 3586859.9 | I68: =+SUM(I64:I67,I62) -> 3741364.9 | J68: =+SUM(J64:J67,J62) -> 3198288.3 | K68: =+SUM(K64:K67,K62) -> 3365121.3
C70: Total Shareholder's Equity | D70: 3784000 | E70: 4161000 | F70: 4654000 | G70: =+F70+G31+G164-G165+G95 -> 6030159.1 | H70: =+G70+H31+H164-H165+H95 -> 7534744.5 | I70: =+H70+I31+I164-I165+I95 -> 9173287.1 | J70: =+I70+J31+J164-J165+J95 -> 10946949 | K70: =+J70+K31+K164-K165+K95 -> 12870531
C71: Total Equity | D71: 3784000 | E71: 4161000 | F71: 4654000 | G71: =+G70+G177 -> 6030159.1 | H71: =+H70+H177 -> 7534744.5 | I71: =+I70+I177 -> 9173287.1 | J71: =+J70+J177 -> 10946949 | K71: =+K70+K177 -> 12870531
C73: Total Liabilities and Equity | D73: 7781000 | E73: 8098000 | F73: 8683000 | G73: =+G71+G68 -> 9531372.6 | H73: =+H71+H68 -> 11121604 | I73: =+I71+I68 -> 12914652 | J73: =+J71+J68 -> 14145237 | K73: =+K71+K68 -> 16235652
C75: Balance Check | D75: =+D56-D73 -> 0 | E75: =+E56-E73 -> 0 | F75: =+F56-F73 -> 0 | G75: =+G56-G73 -> 0 | H75: =+H56-H73 -> 0 | I75: =+I56-I73 -> 0 | J75: =+J56-J73 -> 0 | K75: =+K56-K73 -> 0
C77: Cash Flow Statement | D77: Historical | G77: Projected
D78: =+D$12 -> 44500 | E78: =+E$12 -> 44865 | F78: =+F$12 -> 45230 | G78: =+G$12 -> 45596 | H78: =+H$12 -> 45961 | I78: =+I$12 -> 46326 | J78: =+J$12 -> 46691 | K78: =+K$12 -> 47057
C80: Net Income | D80: 894000 | E80: 1124000 | F80: 1057000 | G80: =+G26+G25 -> 1255159.1 | H80: =+H26+H25 -> 1377585.3 | I80: =+I26+I25 -> 1510876 | J80: =+J26+J25 -> 1648439.2 | K80: =+K26+K25 -> 1796952.4
C81: Depreciation, Depletion & Amortization | D81: 293000 | E81: 223000 | F81: 212000 | G81: =+G28 -> 173968.09 | H81: =+H28 -> 162626.93 | I81: =+I28 -> 160426.57 | J81: =+J28 -> 162432.29 | K81: =+K28 -> 167508.9
C82: Deferred Taxes & Investment Tax Credit | D82: -53000 | E82: 7000 | F82: -3000 | G82: =+F54-G54+G66-F66 -> -34009.286 | H82: =+G54-H54+H66-G66 -> -44889.433 | I82: =+H54-I54+I66-H66 -> -48440.579 | J82: =+I54-J54+J66-I66 -> -48571.77 | K82: =+J54-K54+K66-J66 -> -52305.66
C83: Other Funds | D83: 152000 | E83: 194000 | F83: 161000 | G83: =+G31+F55-G55+G65-F65+G67-F67+G214-G217 -> 156698.5 | H83: =+H31+G55-H55+H65-G65+H67-G67+H214-H217 -> 168465.17 | I83: =+I31+H55-I55+I65-H65+I67-H67+I214-I217 -> 172071.5 | J83: =+J31+I55-J55+J65-I65+J67-I67+J214-J217 -> 171199.78 | K83: =+K31+J55-K55+K65-J65+K67-J67+K214-K217 -> 175741.07
C84: Funds from Operations | D84: 1286000 | E84: 1548000 | F84: 1427000 | G84: =+SUM(G80:G83) -> 1551816.4 | H84: =+SUM(H80:H83) -> 1663788 | I84: =+SUM(I80:I83) -> 1794933.5 | J84: =+SUM(J80:J83) -> 1933499.5 | K84: =+SUM(K80:K83) -> 2087896.7
C85: Changes in Working Capital | D85: 36000 | E85: -404000 | F85: -19000 | G85: =+F47-G47+F48-G48+F49-G49+G59-F59+G60-F60+G61-F61 -> -125538.22 | H85: =+G47-H47+G48-H48+G49-H49+H59-G59+H60-G60+H61-G61 -> -67017.336 | I85: =+H47-I47+H48-I48+H49-I49+I59-H59+I60-H60+I61-H61 -> -72318.992 | J85: =+I47-J47+I48-J48+I49-J49+J59-I59+J60-I60+J61-I61 -> -72514.853 | K85: =+J47-K47+J48-K48+J49-K49+K59-J59+K60-J60+K61-J61 -> -78089.336
C86: Cash Flow From Operating Activities | D86: 1322000 | E86: 1144000 | F86: 1408000 | G86: =+SUM(G84:G85) -> 1426278.2 | H86: =+SUM(H84:H85) -> 1596770.7 | I86: =+SUM(I84:I85) -> 1722614.5 | J86: =+SUM(J84:J85) -> 1860984.6 | K86: =+SUM(K84:K85) -> 2009807.4
C88: Capital Expenditures | D88: -174000 | E88: -185000 | F88: -196000 | G88: =-G154 -> -194376.63 | H88: =-H154 -> -206753 | I88: =-I154 -> -220108.45 | J88: =-J154 -> -233500.07 | K88: =-K154 -> -247921.15
C89: Net Assets from Acquisitions | D89: -178000 | E89: -33000 | F89: -85000 | G89: 0 | H89: 0 | I89: 0 | J89: 0 | K89: 0
C90: Sale of Fixed Assets & Businesses | D90: 0 | E90: 0 | F90: 0 | G90: 0 | H90: 0 | I90: 0 | J90: 0 | K90: 0
C91: Purchase/Sale of Investments | D91: 0 | E91: -33000 | F91: -7000 | G91: =+F52-G52 -> -4916.3946 | H91: =+G52-H52 -> -6489.2325 | I91: =+H52-I52 -> -7002.5875 | J91: =+I52-J52 -> -7021.5524 | K91: =+J52-K52 -> -7561.325
C92: Other Funds | D92: -1000 | E92: 0 | F92: 0 | G92: 0 | H92: 0 | I92: 0 | J92: 0 | K92: 0
C93: Cash Flow From Investing Activities | D93: -353000 | E93: -251000 | F93: -288000 | G93: =+SUM(G88:G92) -> -199293.02 | H93: =+SUM(H88:H92) -> -213242.23 | I93: =+SUM(I88:I92) -> -227111.04 | J93: =+SUM(J88:J92) -> -240521.62 | K93: =+SUM(K88:K92) -> -255482.48
C95: Change in Capital Stock | D95: -614000 | E95: -786000 | F95: -635000 | G95: 0 | H95: 0 | I95: 0 | J95: 0 | K95: 0
C96: Issuance/Reduction of Debt, Net | D96: 0 | E96: 0 | F96: 0 | G96: =+G192-F192+G200-F200+G201-F201 -> -541468.19 | H96: =+H192-G192+H200-G200+H201-G201 -> -57531.811 | I96: =+I192-H192+I200-H200+I201-H201 -> 0 | J96: =+J192-I192+J200-I200+J201-I201 -> -698000 | K96: =+K192-J192+K200-J200+K201-J201 -> 0
C97: Dividends | D97: 0 | E97: 0 | F97: 0 | G97: =-G165 -> 0 | H97: =-H165 -> 0 | I97: =-I165 -> 0 | J97: =-J165 -> 0 | K97: =-K165 -> 0
C98: Other Funds | D98: -57000 | E98: -75000 | F98: -52000 | G98: 0 | H98: 0 | I98: 0 | J98: 0 | K98: 0
C99: Cash Flow From Financing Activities | D99: -671000 | E99: -861000 | F99: -687000 | G99: =+SUM(G95:G98) -> -541468.19 | H99: =+SUM(H95:H98) -> -57531.811 | I99: =+SUM(I95:I98) -> 0 | J99: =+SUM(J95:J98) -> -698000 | K99: =+SUM(K95:K98) -> 0
C101: Effect of Exchange Rate on Cash and Equivalents | D101: 3000 | E101: -43000 | F101: -2000 | G101: 0 | H101: 0 | I101: 0 | J101: 0 | K101: 0
C103: Net Change in Cash During Period | D103: 301000 | E103: -11000 | F103: 431000 | G103: =+G86+G93+G99+G101 -> 685517 | H103: =+H86+H93+H99+H101 -> 1325996.6 | I103: =+I86+I93+I99+I101 -> 1495503.4 | J103: =+J86+J93+J99+J101 -> 922463.02 | K103: =+K86+K93+K99+K101 -> 1754324.9
C105: Line Item Schedules
C107: Current Assets Schedule | D107: Historical | G107: Projected
D108: =+D$12 -> 44500 | E108: =+E$12 -> 44865 | F108: =+F$12 -> 45230 | G108: =+G$12 -> 45596 | H108: =+H$12 -> 45961 | I108: =+I$12 -> 46326 | J108: =+J$12 -> 46691 | K108: =+K$12 -> 47057
C110: Accounts Receivable
C111: Beginning of Period | E111: =+D113 -> 735000 | F111: =+E113 -> 905000 | G111: =+F113 -> 900000 | H111: =+G113 -> 945616.03 | I111: =+H113 -> 1005825.4 | J111: =+I113 -> 1070797.9 | K111: =+J113 -> 1135946.3
C112: Increase (Decrease) | E112: =+E113-E111 -> 170000 | F112: =+F113-F111 -> -5000 | G112: =+G113-G111 -> 45616.032 | H112: =+H113-H111 -> 60209.374 | I112: =+I113-I111 -> 64972.461 | J112: =+J113-J111 -> 65148.425 | K112: =+K113-K111 -> 70156.623
C113: End of Period | D113: =+D47 -> 735000 | E113: =+E47 -> 905000 | F113: =+F47 -> 900000 | G113: =+IF($E$115=1,F113*(1+G117),IF($E$115=2,G119*G118/365,"NA")) -> 945616.03 | H113: =+IF($E$115=1,G113*(1+H117),IF($E$115=2,H119*H118/365,"NA")) -> 1005825.4 | I113: =+IF($E$115=1,H113*(1+I117),IF($E$115=2,I119*I118/365,"NA")) -> 1070797.9 | J113: =+IF($E$115=1,I113*(1+J117),IF($E$115=2,J119*J118/365,"NA")) -> 1135946.3 | K113: =+IF($E$115=1,J113*(1+K117),IF($E$115=2,K119*K118/365,"NA")) -> 1206102.9
C115: A/R Forecasting Approach (1=Rev Growth, 2=DSO) | E115: 1
C117: Revenue Growth Rate (Approach 1) | E117: =+E34 -> 0.096943938 | F117: =+F34 -> 0.0081180812 | G117: =+G34 -> 0.05068448 | H117: =+H34 -> 0.063672116 | I117: =+I34 -> 0.064596162 | J117: =+J34 -> 0.060841011 | K117: =+K34 -> 0.061760511
C118: Days Sales Outstanding (Approach 2) | D118: =+D113*365/D119 -> 54.295689 | E118: =+E113*365/E119 -> 60.945572 | F118: =+F113*365/F119 -> 60.120791 | G118: =+'Revenue Build & Growth Drivers'!G48 -> 60 | H118: =+'Revenue Build & Growth Drivers'!H48 -> 60 | I118: =+'Revenue Build & Growth Drivers'!I48 -> 60 | J118: =+'Revenue Build & Growth Drivers'!J48 -> 60 | K118: =+'Revenue Build & Growth Drivers'!K48 -> 60
C119: Revenue | D119: =+D14 -> 4941000 | E119: =+E14 -> 5420000 | F119: =+F14 -> 5464000 | G119: =+G14 -> 5740940 | H119: =+H14 -> 6106477.8 | I119: =+I14 -> 6500932.8 | J119: =+J14 -> 6896456.2 | K119: =+K14 -> 7322384.8
C121: Inventories
C122: Beginning of Period | E122: =+D124 -> 777000 | F122: =+E124 -> 1057000 | G122: =+F124 -> 1195000 | H122: =+G124 -> 1234523.5 | I122: =+H124 -> 1313128.2 | J122: =+I124 -> 1397951.2 | K122: =+J124 -> 1483004
C123: Increase (Decrease) | E123: =+E124-E122 -> 280000 | F123: =+F124-F122 -> 138000 | G123: =+G124-G122 -> 39523.473 | H123: =+H124-H122 -> 78604.722 | I123: =+I124-I122 -> 84823.042 | J123: =+J124-J122 -> 85052.767 | K123: =+K124-K122 -> 91591.085
C124: End of Period | D124: =+D48 -> 777000 | E124: =+E48 -> 1057000 | F124: =+F48 -> 1195000 | G124: =+IF($E$126=1,F124*(1+G128),IF($E$126=2,G130/G129,"NA")) -> 1234523.5 | H124: =+IF($E$126=1,G124*(1+H128),IF($E$126=2,H130/H129,"NA")) -> 1313128.2 | I124: =+IF($E$126=1,H124*(1+I128),IF($E$126=2,I130/I129,"NA")) -> 1397951.2 | J124: =+IF($E$126=1,I124*(1+J128),IF($E$126=2,J130/J129,"NA")) -> 1483004 | K124: =+IF($E$126=1,J124*(1+K128),IF($E$126=2,K130/K129,"NA")) -> 1574595.1
C126: Inventory Forecasting Approach (1=Cost of Sales Growth, 2=Turnover) | E126: 1
C128: Cost of Sales Growth Rate (Approach 1) | E128: =+E130/D130-1 -> 0.059797117 | F128: =+F130/E130-1 -> -0.020151134 | G128: =+G130/F130-1 -> 0.033074036 | H128: =+H130/G130-1 -> 0.063672116 | I128: =+I130/H130-1 -> 0.064596162 | J128: =+J130/I130-1 -> 0.060841011 | K128: =+K130/J130-1 -> 0.061760511
...

Sheet Integrated DCF Model
C2: ="Discounted Cash Flow Model For "&D5 -> Discounted Cash Flow Model For Keysight Technologies, Inc.
C3: $ in thousands except per share | J3: Values
C5: Company Name | D5: ='Revenue Build & Growth Drivers'!D5 -> Keysight Technologies, Inc. | G5: Basic Shares Outstanding | J5: =+D66 -> 175044.6
C6: Ticker | D6: ='Revenue Build & Growth Drivers'!D6 -> KEYS | G6: Fully Diluted Shares Outstanding | J6: =+D71 -> 178193.6
C7: Valuation Date | D7: ='Revenue Build & Growth Drivers'!D7 -> 45394 | G7: Discount Rate (WACC) | J7: =+'WACC Build'!D45 -> 0.10684718
C8: Latest Adj. Closing Share Price Date | D8: ='Revenue Build & Growth Drivers'!D8 -> 45393 | G8: Midyear Adjustment (1=on, 0=off) | J8: 0
C9: Latest Adj. Closing Share Price | D9: ='Revenue Build & Growth Drivers'!D9 -> 160.14
C11: Unlevered Free Cash Flow | E11: Historical | H11: Projected | N11: 5 Year
E12: ='Financial Statement Model'!D12 -> 44500 | F12: ='Financial Statement Model'!E12 -> 44865 | G12: ='Financial Statement Model'!F12 -> 45230 | H12: ='Financial Statement Model'!G12 -> 45596 | I12: ='Financial Statement Model'!H12 -> 45961 | J12: ='Financial Statement Model'!I12 -> 46326 | K12: ='Financial Statement Model'!J12 -> 46691 | L12: ='Financial Statement Model'!K12 -> 47057 | N12: CAGR
C14: Total Revenues | E14: =+'Financial Statement Model'!D14 -> 4941000 | F14: =+'Financial Statement Model'!E14 -> 5420000 | G14: =+'Financial Statement Model'!F14 -> 5464000 | H14: =+'Financial Statement Model'!G14 -> 5740940 | I14: =+'Financial Statement Model'!H14 -> 6106477.8 | J14: =+'Financial Statement Model'!I14 -> 6500932.8 | K14: =+'Financial Statement Model'!J14 -> 6896456.2 | L14: =+'Financial Statement Model'!K14 -> 7322384.8
C15: YoY Growth Rate (%) | F15: =+F14/E14-1 -> 0.096943938 | G15: =+G14/F14-1 -> 0.0081180812 | H15: =+H14/G14-1 -> 0.05068448 | I15: =+I14/H14-1 -> 0.063672116 | J15: =+J14/I14-1 -> 0.064596162 | K15: =+K14/J14-1 -> 0.060841011 | L15: =+L14/K14-1 -> 0.061760511
C17: Gross Profit | E17: =+'Financial Statement Model'!D16 -> 3068000 | F17: =+'Financial Statement Model'!E16 -> 3435000 | G17: =+'Financial Statement Model'!F16 -> 3519000 | H17: =+'Financial Statement Model'!G16 -> 3731611 | I17: =+'Financial Statement Model'!H16 -> 3969210.6 | J17: =+'Financial Statement Model'!I16 -> 4225606.3 | K17: =+'Financial Statement Model'!J16 -> 4482696.5 | L17: =+'Financial Statement Model'!K16 -> 4759550.1
C18: Gross Margin (%) | E18: =+E17/E$14 -> 0.62092694 | F18: =+F17/F$14 -> 0.63376384 | G18: =+G17/G$14 -> 0.64403367 | H18: =+H17/H$14 -> 0.65 | I18: =+I17/I$14 -> 0.65 | J18: =+J17/J$14 -> 0.65 | K18: =+K17/K$14 -> 0.65 | L18: =+L17/L$14 -> 0.65
C20: EBITDA | E20: =+'Financial Statement Model'!D29 -> 1372000 | F20: =+'Financial Statement Model'!E29 -> 1556000 | G20: =+'Financial Statement Model'!F29 -> 1606000 | H20: =+'Financial Statement Model'!G29 -> 1724021.9 | I20: =+'Financial Statement Model'!H29 -> 1811375.9 | J20: =+'Financial Statement Model'!I29 -> 1915678.4 | K20: =+'Financial Statement Model'!J29 -> 2024475.4 | L20: =+'Financial Statement Model'!K29 -> 2144552.8 | N20: =+_xlfn.RRI(YEAR($L$12)-YEAR($G$12),G20,L20) -> 0.059542156
C21: EBITDA Margin (%) | E21: =+E20/E$14 -> 0.27767658 | F21: =+F20/F$14 -> 0.28708487 | G21: =+G20/G$14 -> 0.29392387 | H21: =+H20/H$14 -> 0.30030307 | I21: =+I20/I$14 -> 0.29663187 | J21: =+J20/J$14 -> 0.29467747 | K21: =+K20/K$14 -> 0.29355301 | L21: =+L20/L$14 -> 0.29287628
C23: Operating Profit (EBIT) | E23: =+'Financial Statement Model'!D19 -> 1081000 | F23: =+'Financial Statement Model'!E19 -> 1336000 | G23: =+'Financial Statement Model'!F19 -> 1396000 | H23: =+'Financial Statement Model'!G19 -> 1550053.8 | I23: =+'Financial Statement Model'!H19 -> 1648749 | J23: =+'Financial Statement Model'!I19 -> 1755251.9 | K23: =+'Financial Statement Model'!J19 -> 1862043.2 | L23: =+'Financial Statement Model'!K19 -> 1977043.9
C24: EBIT Margin (%) | E24: =+E23/E$14 -> 0.21878162 | F24: =+F23/F$14 -> 0.24649446 | G24: =+G23/G$14 -> 0.25549048 | H24: =+H23/H$14 -> 0.27 | I24: =+I23/I$14 -> 0.27 | J24: =+J23/J$14 -> 0.27 | K24: =+K23/K$14 -> 0.27 | L24: =+L23/L$14 -> 0.27
C26: Tax on EBIT | E26: =+E23*E27 -> 124154.46 | F26: =+F23*F27 -> 167389.88 | G26: =+G23*G27 -> 308621.96 | H26: =+H23*H27 -> 342679.54 | I26: =+I23*I27 -> 364498.67 | J26: =+J23*J27 -> 388043.89 | K26: =+K23*K27 -> 411652.87 | L26: =+L23*L27 -> 437076.76
C27: Tax Rate (%) | E27: =+'Financial Statement Model'!D41 -> 0.11485149 | F27: =+'Financial Statement Model'!E41 -> 0.12529183 | G27: =+'Financial Statement Model'!F41 -> 0.2210759 | H27: =+'Financial Statement Model'!G41 -> 0.2210759 | I27: =+'Financial Statement Model'!H41 -> 0.2210759 | J27: =+'Financial Statement Model'!I41 -> 0.2210759 | K27: =+'Financial Statement Model'!J41 -> 0.2210759 | L27: =+'Financial Statement Model'!K41 -> 0.2210759
C29: NOPAT/EBIAT | E29: =+E23-E26 -> 956845.54 | F29: =+F23-F26 -> 1168610.1 | G29: =+G23-G26 -> 1087378 | H29: =+H23-H26 -> 1207374.3 | I29: =+I23-I26 -> 1284250.3 | J29: =+J23-J26 -> 1367208 | K29: =+K23-K26 -> 1450390.3 | L29: =+L23-L26 -> 1539967.1
C31: Plus: Depreciation and Amortization | F31: =+'Financial Statement Model'!E28 -> 220000 | G31: =+'Financial Statement Model'!F28 -> 210000 | H31: =+'Financial Statement Model'!G28 -> 173968.09 | I31: =+'Financial Statement Model'!H28 -> 162626.93 | J31: =+'Financial Statement Model'!I28 -> 160426.57 | K31: =+'Financial Statement Model'!J28 -> 162432.29 | L31: =+'Financial Statement Model'!K28 -> 167508.9
C32: Plus: Stock Compensation | F32: =+'Financial Statement Model'!E31 -> 125000 | G32: =+'Financial Statement Model'!F31 -> 135000 | H32: =+'Financial Statement Model'!G31 -> 121000 | I32: =+'Financial Statement Model'!H31 -> 127000 | J32: =+'Financial Statement Model'!I31 -> 127666.67 | K32: =+'Financial Statement Model'!J31 -> 125222.22 | L32: =+'Financial Statement Model'!K31 -> 126629.63
C33: Less: Change in Net Working Capital | F33: =F52 -> 332000 | G33: =G52 -> 97000 | H33: =H52 -> 35538.223 | I33: =I52 -> 67017.336 | J33: =J52 -> 72318.992 | K33: =K52 -> 72514.853 | L33: =L52 -> 78089.336
C34: Less: Capital Expenditures | F34: =+'Financial Statement Model'!E154 -> 185000 | G34: =+'Financial Statement Model'!F154 -> 196000 | H34: =+'Financial Statement Model'!G154 -> 194376.63 | I34: =+'Financial Statement Model'!H154 -> 206753 | J34: =+'Financial Statement Model'!I154 -> 220108.45 | K34: =+'Financial Statement Model'!J154 -> 233500.07 | L34: =+'Financial Statement Model'!K154 -> 247921.15
C36: Unlevered Free Cash Flow (UFCF) | F36: =+F29+F31+F32-F33-F34 -> 996610.12 | G36: =+G29+G31+G32-G33-G34 -> 1139378 | H36: =+H29+H31+H32-H33-H34 -> 1272427.5 | I36: =+I29+I31+I32-I33-I34 -> 1300106.9 | J36: =+J29+J31+J32-J33-J34 -> 1362873.8 | K36: =+K29+K31+K32-K33-K34 -> 1432029.9 | L36: =+L29+L31+L32-L33-L34 -> 1508095.2 | N36: =+_xlfn.RRI(YEAR($L$12)-YEAR($G$12),G36,L36) -> 0.057674859
C38: Net Working Capital Schedule | E38: Historical | H38: Projected
E39: ='Financial Statement Model'!D12 -> 44500 | F39: ='Financial Statement Model'!E12 -> 44865 | G39: ='Financial Statement Model'!F12 -> 45230 | H39: ='Financial Statement Model'!G12 -> 45596 | I39: ='Financial Statement Model'!H12 -> 45961 | J39: ='Financial Statement Model'!I12 -> 46326 | K39: ='Financial Statement Model'!J12 -> 46691 | L39: ='Financial Statement Model'!K12 -> 47057
C41: Short-Term Receivables | E41: =+'Financial Statement Model'!D47 -> 735000 | F41: =+'Financial Statement Model'!E47 -> 905000 | G41: =+'Financial Statement Model'!F47 -> 900000 | H41: =+'Financial Statement Model'!G47 -> 945616.03 | I41: =+'Financial Statement Model'!H47 -> 1005825.4 | J41: =+'Financial Statement Model'!I47 -> 1070797.9 | K41: =+'Financial Statement Model'!J47 -> 1135946.3 | L41: =+'Financial Statement Model'!K47 -> 1206102.9
C42: Inventories | E42: =+'Financial Statement Model'!D48 -> 777000 | F42: =+'Financial Statement Model'!E48 -> 1057000 | G42: =+'Financial Statement Model'!F48 -> 1195000 | H42: =+'Financial Statement Model'!G48 -> 1234523.5 | I42: =+'Financial Statement Model'!H48 -> 1313128.2 | J42: =+'Financial Statement Model'!I48 -> 1397951.2 | K42: =+'Financial Statement Model'!J48 -> 1483004 | L42: =+'Financial Statement Model'!K48 -> 1574595.1
C43: Other Current Assets | E43: =+'Financial Statement Model'!D49 -> 270000 | F43: =+'Financial Statement Model'!E49 -> 230000 | G43: =+'Financial Statement Model'!F49 -> 242000 | H43: =+'Financial Statement Model'!G49 -> 254265.64 | I43: =+'Financial Statement Model'!H49 -> 270455.28 | J43: =+'Financial Statement Model'!I49 -> 287925.65 | K43: =+'Financial Statement Model'!J49 -> 305443.34 | L43: =+'Financial Statement Model'!K49 -> 324307.67
C44: Current Assets (Ex. Cash) | E44: =SUM(E41:E43) -> 1782000 | F44: =SUM(F41:F43) -> 2192000 | G44: =SUM(G41:G43) -> 2337000 | H44: =SUM(H41:H43) -> 2434405.1 | I44: =SUM(I41:I43) -> 2589408.9 | J44: =SUM(J41:J43) -> 2756674.8 | K44: =SUM(K41:K43) -> 2924393.6 | L44: =SUM(L41:L43) -> 3105005.7
C46: Accounts Payable | E46: =+'Financial Statement Model'!D59 -> 287000 | F46: =+'Financial Statement Model'!E59 -> 348000 | G46: =+'Financial Statement Model'!F59 -> 286000 | H46: =+'Financial Statement Model'!G59 -> 295459.17 | I46: =+'Financial Statement Model'!H59 -> 314271.69 | J46: =+'Financial Statement Model'!I59 -> 334572.43 | K46: =+'Financial Statement Model'!J59 -> 354928.15 | L46: =+'Financial Statement Model'!K59 -> 376848.7
C47: Other Current Liabilities | E47: =+'Financial Statement Model'!D61 -> 907000 | F47: =+'Financial Statement Model'!E61 -> 924000 | G47: =+'Financial Statement Model'!F61 -> 1034000 | H47: =+'Financial Statement Model'!G61 -> 1086407.8 | I47: =+'Financial Statement Model'!H61 -> 1155581.6 | J47: =+'Financial Statement Model'!I61 -> 1230227.8 | K47: =+'Financial Statement Model'!J61 -> 1305076.1 | L47: =+'Financial Statement Model'!K61 -> 1385678.2
C48: Current Liabilities | E48: =SUM(E46:E47) -> 1194000 | F48: =SUM(F46:F47) -> 1272000 | G48: =SUM(G46:G47) -> 1320000 | H48: =SUM(H46:H47) -> 1381866.9 | I48: =SUM(I46:I47) -> 1469853.3 | J48: =SUM(J46:J47) -> 1564800.2 | K48: =SUM(K46:K47) -> 1660004.2 | L48: =SUM(L46:L47) -> 1762526.9
C50: Net Working Capital | E50: =+E44-E48 -> 588000 | F50: =+F44-F48 -> 920000 | G50: =+G44-G48 -> 1017000 | H50: =+H44-H48 -> 1052538.2 | I50: =+I44-I48 -> 1119555.6 | J50: =+J44-J48 -> 1191874.6 | K50: =+K44-K48 -> 1264389.4 | L50: =+L44-L48 -> 1342478.7
C52: Change in Net Working Capital | F52: =+F50-E50 -> 332000 | G52: =+G50-F50 -> 97000 | H52: =+H50-G50 -> 35538.223 | I52: =+I50-H50 -> 67017.336 | J52: =+J50-I50 -> 72318.992 | K52: =+K50-J50 -> 72514.853 | L52: =+L50-K50 -> 78089.336
C54: ="Present Value of UFCFs as of "&TEXT(D7,("mmm dd, yyyy")) -> Present Value of UFCFs as of Apr 12, 2024 | F54: Stub % | H54: Stub Year | I54: Year 2 | J54: Year 3 | K54: Year 4 | L54: Year 5
C55: Dates for Discounting UFCF | F55: =YEARFRAC(D7,H55,1) -> 0.55191257 | H55: =IF($J$8=0,H$12,AVERAGE(D7,H12)) -> 45596 | I55: =IF($J$8=0,I$12,AVERAGE(H12:I12)) -> 45961 | J55: =IF($J$8=0,J$12,AVERAGE(I12:J12)) -> 46326 | K55: =IF($J$8=0,K$12,AVERAGE(J12:K12)) -> 46691 | L55: =IF($J$8=0,L$12,AVERAGE(K12:L12)) -> 47057
C57: Periods for Discounting UFCF | H57: =+YEARFRAC($D$7,H55,1) -> 0.55191257 | I57: =+YEARFRAC($D$7,I55,1) -> 1.5512996 | J57: =+YEARFRAC($D$7,J55,1) -> 2.5510949 | K57: =+YEARFRAC($D$7,K55,1) -> 3.5509925 | L57: =+YEARFRAC($D$7,L55,1) -> 4.5511768
C59: Stub-adjusted Unlevered Free Cash Flow (UFCF) | H59: =+H36*F55 -> 702268.73 | I59: =+I36 -> 1300106.9 | J59: =+J36 -> 1362873.8 | K59: =+K36 -> 1432029.9 | L59: =+L36 -> 1508095.2
C61: PV of Stub-adjusted UFCFs | H61: =+H59/(1+$J$7)^H57 -> 664004.15 | I61: =+I59/(1+$J$7)^I57 -> 1110672.2 | J61: =+J59/(1+$J$7)^J57 -> 1051922.7 | K61: =+K59/(1+$J$7)^K57 -> 998612.78 | L61: =+L59/(1+$J$7)^L57 -> 950119
C63: Basic to Fully Diluted Shares Bridge (in 000s)
C66: Basic Shares | D66: 175044.6
C67: Restricted Stock | D67: 2149
C68: Options/Warrants | D68: 1000
C69: Convertible Debt | D69: 0
C70: Convertible Preferred Stock | D70: 0
C71: Fully Diluted Shares Outstanding | D71: =SUM(D66:D70) -> 178193.6
C73: Terminal Value and Equity Value Bridge
C76: Terminal Value - Multiples Method | H76: Terminal Value - Perpetual Growth Method
C78: EV/EBITDA | E78: 22 | H78: Terminal UFCF Growth Rate | L78: 0.06
C80: Implied Terminal Value | E80: =+E78*L20 -> 47180162 | H80: Implied Terminal Value | L80: =+L59*(1+L78)/(J7-L78) -> 34123312
C81: Implied Terminal UFCF Growth Rate | E81: =+(E80*J7-L59)/(E80+L59) -> 0.072563123 | H81: Implied Terminal EV/EBITDA | L81: =+L80/L20 -> 15.911621
C83: Plus: PV of Terminal Value | E83: =+E80/(1+J7)^L57 -> 29724098 | H83: Plus: PV of Terminal Value | L83: =+L80/(1+J7)^L57 -> 21498117
C84: Plus: Sum of PV of Stub-adjusted UFCFs | E84: =+SUM(H61:L61) -> 4775330.8 | H84: Plus: Sum of PV of Stub-adjusted UFCFs | L84: =+SUM(H61:L61) -> 4775330.8
C85: Implied Enterprise Value | E85: =+E83+E84 -> 34499428 | H85: Implied Enterprise Value | L85: =SUM(L83:L84) -> 26273448
C87: % of Implied EV from Terminal Value | E87: =+E83/E85 -> 0.86158232 | H87: % of Implied EV from Terminal Value | L87: =+L83/L85 -> 0.81824499
C89: Plus: Cash and Cash Equivalents | E89: =+'Financial Statement Model'!F46 -> 2472000 | H89: Plus: Cash and Cash Equivalents | L89: =+E89 -> 2472000
C90: Less: Debt & Capital Leases (excl. Operating Leases) | E90: =+'Financial Statement Model'!F192+'Financial Statement Model'!F200+'Financial Statement Model'!F201 -> 1794000 | H90: Less: Debt & Capital Leases (excl. Operating Leases) | L90: =+E90 -> 1794000
C91: Less: Preferred Stock | E91: 0 | H91: Less: Preferred Stock | L91: =+E91 -> 0
C92: Less: Non-controlling Interest | E92: =+'Financial Statement Model'!F177 -> 0 | H92: Less: Non-controlling Interest | L92: =+E92 -> 0
C93: Implied Equity Value | E93: =+E85+E89-E90-E91-E92 -> 35177428 | H93: Implied Equity Value | L93: =+L85+L89-L90-L91-L92 -> 26951448
C95: Implied Share Price | E95: =+E93/D71 -> 197.41129 | H95: Implied Share Price | L95: =+L93/D71 -> 151.24812
C96: Premium (Discount) to Current Price | E96: =+E95/D9-1 -> 0.23274188 | H96: Premium (Discount) to Current Price | L96: =+L95/D9-1 -> -0.055525645
C98: Implied Y1 Multiples | H98: Implied Y1 Multiples
C99: EV / Revenue | E99: =+E$85/$H14 -> 6.0093693 | H99: EV / Revenue | L99: =+L$85/$H14 -> 4.5765063
C100: EV / EBITDA | E100: =+E$85/$H20 -> 20.011015 | H100: EV / EBITDA | L100: =+L$85/$H20 -> 15.239626
C101: EV / EBIT | E101: =+E$85/$H23 -> 22.256923 | H101: EV / EBIT | L101: =+L$85/$H23 -> 16.950023
C103: Data Tables and Football Field
E106: EV/EBITDA Multiple
D107: Discount Rate (WACC) | E107: =E95 -> 197.41129 | F107: =+G107-0.5 -> 20.5 | G107: =+H107-0.5 -> 21 | H107: =+I107-0.5 -> 21.5 | I107: 22 | J107: =+I107+0.5 -> 22.5 | K107: =+J107+0.5 -> 23 | L107: =+K107+0.5 -> 23.5
E108: =+E109-0.5% -> 0.091847179 | F108: 196.98684 | G108: 201.02082 | H108: 205.05479 | I108: 209.08877 | J108: 213.12275 | K108: 217.15672 | L108: 221.1907
E109: =+E110-0.5% -> 0.096847179 | F109: 193.24649 | G109: 197.19745 | H109: 201.1484 | I109: 205.09936 | J109: 209.05032 | K109: 213.00128 | L109: 216.95224
E110: =+E111-0.5% -> 0.10184718 | F110: 189.59777 | G110: 193.46778 | H110: 197.3378 | I110: 201.20782 | J110: 205.07783 | K110: 208.94785 | L110: 212.81787
E111: 0.10684718 | F111: 186.03802 | G111: 189.82911 | H111: 193.6202 | I111: 197.41129 | J111: 201.20237 | K111: 204.99346 | L111: 208.78455
E112: =+E111+0.5% -> 0.11184718 | F112: 182.56467 | G112: 186.27879 | H112: 189.9929 | I112: 193.70702 | J112: 197.42113 | K112: 201.13524 | L112: 204.84936
E113: =+E112+0.5% -> 0.11684718 | F113: 179.17524 | G113: 182.81427 | H113: 186.45331 | I113: 190.09235 | J113: 193.73139 | K113: 197.37043 | L113: 201.00946
E114: =+E113+0.5% -> 0.12184718 | F114: 175.8673 | G114: 179.43311 | H114: 182.99891 | I114: 186.56472 | J114: 190.13052 | K114: 193.69633 | L114: 197.26213
E116: Terminal UFCF Growth Rate
D117: Discount Rate (WACC) | E117: =L95 -> 151.24812 | F117: =+G117-0.5% -> 0.045 | G117: =+H117-0.5% -> 0.05 | H117: =+I117-0.5% -> 0.055 | I117: 0.06 | J117: =+I117+0.5% -> 0.065 | K117: =+J117+0.5% -> 0.07 | L117: =+K117+0.5% -> 0.075
E118: =+E119-0.5% -> 0.091847179 | F118: 158.15141 | G118: 173.9507 | H118: 194.03777 | I118: 220.43218 | J118: 256.65794 | K118: 309.46514 | L118: 393.61718
E119: =+E120-0.5% -> 0.096847179 | F119: 143.25656 | G119: 155.80334 | H119: 171.34835 | I119: 191.11214 | J119: 217.08175 | K119: 252.72449 | L119: 304.6818
E120: =+E121-0.5% -> 0.10184718 | F120: 130.98287 | G120: 141.15688 | H120: 153.50263 | I120: 168.79859 | J120: 188.24573 | K120: 213.79927 | L120: 248.87095
E121: 0.10684718 | F121: 120.69459 | G121: 129.08754 | H121: 139.09928 | I121: 151.24812 | J121: 166.30011 | K121: 185.43708 | L121: 210.58305
E122: =+E121+0.5% -> 0.11184718 | F122: 111.9462 | G122: 118.97027 | H122: 127.22996 | I122: 137.08273 | J122: 149.03867 | K122: 163.85166 | L122: 182.68477
E123: =+E122+0.5% -> 0.11684718 | F123: 104.41619 | G123: 110.36704 | H123: 117.28009 | I123: 125.40921 | J123: 135.10623 | K123: 146.87318 | L123: 161.45201
E124: =+E123+0.5% -> 0.12184718 | F124: 97.866729 | G124: 102.96175 | H124: 108.81895 | I124: 115.6232 | J124: 123.62439 | K124: 133.1688 | L124: 144.75056

Sheet WACC Build
C2: ="WACC Build For "&D5 -> WACC Build For Keysight Technologies, Inc.
C3: $ in thousands except per share | J3: Values
C5: Company Name | D5: ='Revenue Build & Growth Drivers'!D5 -> Keysight Technologies, Inc. | G5: Basic Shares Outstanding | J5: =+'Integrated DCF Model'!D66 -> 175044.6
C6: Ticker | D6: ='Revenue Build & Growth Drivers'!D6 -> KEYS | G6: Fully Diluted Shares Outstanding | J6: =+'Integrated DCF Model'!D71 -> 178193.6
C7: Valuation Date | D7: ='Revenue Build & Growth Drivers'!D7 -> 45394
C8: Latest Adj. Closing Share Price Date | D8: ='Revenue Build & Growth Drivers'!D8 -> 45393
C9: Latest Adj. Closing Share Price | D9: ='Revenue Build & Growth Drivers'!D9 -> 160.14
C11: Cost of Debt Calculation | F11: Beta (β) Calculator
C14: Interest on Short-term Bank Credit | D14: =+'Financial Statement Model'!F195 -> 0 | F14: =D5&" ("&D6&")" -> Keysight Technologies, Inc. (KEYS) | J14: S&P 500 Index
C15: Interest on Long-term Debt | D15: =+'Financial Statement Model'!F202 -> 78000 | F15: Date | G15: Adj. Close Price | H15: Return (%) | J15: Date | K15: Adj. Close Price | L15: Return (%)
C16: Total Interest Expenses | D16: =SUM(D14:D15) -> 78000 | F16: 44317 | G16: 142.38001 | J16: 44317 | K16: 4204.1099
F17: 44348 | G17: 154.41 | H17: =+G17/G16-1 -> 0.084492194 | J17: 44348 | K17: 4297.5 | L17: =+K17/K16-1 -> 0.02221401
C18: Short-term Bank Credit/Revolver | D18: =+AVERAGE('Financial Statement Model'!E192:F192) -> 0 | F18: 44378 | G18: 164.55 | H18: =+G18/G17-1 -> 0.065669314 | J18: 44378 | K18: 4395.2598 | L18: =+K18/K17-1 -> 0.022748055
C19: Current Portion of LT Debt & Finance leases | D19: =+AVERAGE('Financial Statement Model'!E200:F200) -> 299500 | F19: 44409 | G19: 179.38001 | H19: =+G19/G18-1 -> 0.090124593 | J19: 44409 | K19: 4522.6802 | L19: =+K19/K18-1 -> 0.028990416
C20: LT Debt & Finance leases (Ex. Current Portion) | D20: =+AVERAGE('Financial Statement Model'!E201:F201) -> 1494000 | F20: 44440 | G20: 164.28999 | H20: =+G20/G19-1 -> -0.084123155 | J20: 44440 | K20: 4307.54 | L20: =+K20/K19-1 -> -0.047569169
C21: Total Debt | D21: =SUM(D18:D20) -> 1793500 | F21: 44470 | G21: 180.02 | H21: =+G21/G20-1 -> 0.095745399 | J21: 44470 | K21: 4605.3799 | L21: =+K21/K20-1 -> 0.069143836
F22: 44501 | G22: 194.48 | H22: =+G22/G21-1 -> 0.080324362 | J22: 44501 | K22: 4567 | L22: =+K22/K21-1 -> -0.0083337062
C23: Pre-tax Cost of Debt | D23: =+D16/D21 -> 0.043490382 | F23: 44531 | G23: 206.51 | H23: =+G23/G22-1 -> 0.061857257 | J23: 44531 | K23: 4766.1802 | L23: =+K23/K22-1 -> 0.043612914
C24: Effective Tax Rate | D24: =+IF('Financial Statement Model'!F41<0,AVERAGEIFS('Financial Statement Model'!D41:F41,'Financial Statement Model'!D41:F41,">0"),'Financial Statement Model'!F41) -> 0.2210759 | F24: 44562 | G24: 168.82001 | H24: =+G24/G23-1 -> -0.18250927 | J24: 44562 | K24: 4515.5498 | L24: =+K24/K23-1 -> -0.052585165
F25: 44593 | G25: 157.36999 | H25: =+G25/G24-1 -> -0.067823786 | J25: 44593 | K25: 4373.9399 | L25: =+K25/K24-1 -> -0.031360492
C26: Effective Cost of Debt | D26: =+D23*(1-D24) -> 0.033875706 | F26: 44621 | G26: 157.97 | H26: =+G26/G25-1 -> 0.003812709 | J26: 44621 | K26: 4530.4102 | L26: =+K26/K25-1 -> 0.035773288
F27: 44652 | G27: 140.27 | H27: =+G27/G26-1 -> -0.11204657 | J27: 44652 | K27: 4131.9302 | L27: =+K27/K26-1 -> -0.087956712
C28: Cost of Equity Calculation | F28: 44682 | G28: 145.60001 | H28: =+G28/G27-1 -> 0.03799816 | J28: 44682 | K28: 4132.1499 | L28: =+K28/K27-1 -> 5.3177569e-05
F29: 44713 | G29: 137.85001 | H29: =+G29/G28-1 -> -0.05322802 | J29: 44713 | K29: 3785.3799 | L29: =+K29/K28-1 -> -0.08392
F30: 44743 | G30: 162.60001 | H30: =+G30/G29-1 -> 0.17954297 | J30: 44743 | K30: 4130.29 | L30: =+K30/K29-1 -> 0.091116392
C31: Equity Risk Premium | D31: 0.055 | F31: 44774 | G31: 163.89 | H31: =+G31/G30-1 -> 0.007933536 | J31: 44774 | K31: 3955 | L31: =+K31/K30-1 -> -0.042440128
C32: Risk-free Rate | D32: 0.0456 | F32: 44805 | G32: 157.36 | H32: =+G32/G31-1 -> -0.039843786 | J32: 44805 | K32: 3585.6201 | L32: =+K32/K31-1 -> -0.093395672
C33: Company Beta | D33: =+L52 -> 1.1969956 | F33: 44835 | G33: 174.14999 | H33: =+G33/G32-1 -> 0.10669797 | J33: 44835 | K33: 3871.98 | L33: =+K33/K32-1 -> 0.079863414
F34: 44866 | G34: 180.89 | H34: =+G34/G33-1 -> 0.038702298 | J34: 44866 | K34: 4080.1101 | L34: =+K34/K33-1 -> 0.053752893
C35: Cost of Equity | D35: =+D32+D33*D31 -> 0.11143476 | F35: 44896 | G35: 171.07001 | H35: =+G35/G34-1 -> -0.054287092 | J35: 44896 | K35: 3839.5 | L35: =+K35/K34-1 -> -0.058971474
F36: 44927 | G36: 179.35001 | H36: =+G36/G35-1 -> 0.048401231 | J36: 44927 | K36: 4076.6001 | L36: =+K36/K35-1 -> 0.061752858
C37: Capital Structure and WACC | F37: 44958 | G37: 159.96001 | H37: =+G37/G36-1 -> -0.10811262 | J37: 44958 | K37: 3970.1499 | L37: =+K37/K36-1 -> -0.026112494
F38: 44986 | G38: 161.48 | H38: =+G38/G37-1 -> 0.0095023064 | J38: 44986 | K38: 4109.3101 | L38: =+K38/K37-1 -> 0.035051613
F39: 45017 | G39: 144.64 | H39: =+G39/G38-1 -> -0.10428534 | J39: 45017 | K39: 4169.48 | L39: =+K39/K38-1 -> 0.014642341
C40: Total Debt | D40: =+'Financial Statement Model'!F192+'Financial Statement Model'!F200+'Financial Statement Model'!F201 -> 1794000 | F40: 45047 | G40: 161.8 | H40: =+G40/G39-1 -> 0.11863941 | J40: 45047 | K40: 4179.8301 | L40: =+K40/K39-1 -> 0.0024823475
C41: % of Total Capital | D41: =+D40/(D40+D42) -> 0.059149506 | F41: 45078 | G41: 167.45 | H41: =+G41/G40-1 -> 0.034919616 | J41: 45078 | K41: 4450.3799 | L41: =+K41/K40-1 -> 0.064727465
C42: Equity Value | D42: =+D9*J6 -> 28535924 | F42: 45108 | G42: 161.08 | H42: =+G42/G41-1 -> -0.038041177 | J42: 45108 | K42: 4588.96 | L42: =+K42/K41-1 -> 0.031138932
C43: % of Total Capital | D43: =+D42/(D40+D42) -> 0.94085049 | F43: 45139 | G43: 133.3 | H43: =+G43/G42-1 -> -0.17246088 | J43: 45139 | K43: 4507.6602 | L43: =+K43/K42-1 -> -0.01771639
F44: 45170 | G44: 132.31 | H44: =+G44/G43-1 -> -0.0074268941 | J44: 45170 | K44: 4288.0498 | L44: =+K44/K43-1 -> -0.048719367
C45: Weighted Average Cost of Capital (WACC) | D45: =D41*D26+D43*D35 -> 0.10684718 | F45: 45200 | G45: 122.05 | H45: =+G45/G44-1 -> -0.077545122 | J45: 45200 | K45: 4193.7998 | L45: =+K45/K44-1 -> -0.021979689
F46: 45231 | G46: 135.89 | H46: =+G46/G45-1 -> 0.11339611 | J46: 45231 | K46: 4567.7998 | L46: =+K46/K45-1 -> 0.089179269
F47: 45261 | G47: 159.09 | H47: =+G47/G46-1 -> 0.1707263 | J47: 45261 | K47: 4769.8301 | L47: =+K47/K46-1 -> 0.044229231
F48: 45292 | G48: 153.26 | H48: =+G48/G47-1 -> -0.036645931 | J48: 45292 | K48: 4845.6499 | L48: =+K48/K47-1 -> 0.015895708
F49: 45323 | G49: 154.3 | H49: =+G49/G48-1 -> 0.0067859065 | J49: 45323 | K49: 5096.27 | L49: =+K49/K48-1 -> 0.051720641
F50: 45352 | G50: 156.38001 | H50: =+G50/G49-1 -> 0.013480246 | J50: 45352 | K50: 5254.3501 | L50: =+K50/K49-1 -> 0.03101878
F51: 45383 | G51: 147.94 | H51: =+G51/G50-1 -> -0.053971114 | J51: 45383 | K51: 5035.6899 | L51: =+K51/K50-1 -> -0.041615072
K52: Company Beta (3Y Monthly) >> | L52: =+SLOPE(H17:H51,L17:L51) -> 1.1969956
