Workbook
Name Discount_Rate: 'Integrated DCF Model'!$E$10
Name Discount_Rate: #REF!
Name IQ_CH: 110000
Name IQ_CQ: 5000
Name IQ_CY: 10000
Name IQ_DAILY: 500000
Name IQ_FH: 100000
Name IQ_FQ: 500
Name IQ_FWD_CY: 10001
Name IQ_FWD_CY1: 10002
Name IQ_FWD_CY2: 10003
Name IQ_FWD_FY: 1001
Name IQ_FWD_FY1: 1002
Name IQ_FWD_FY2: 1003
Name IQ_FWD_Q: 501
Name IQ_FWD_Q1: 502
Name IQ_FWD_Q2: 503
Name IQ_FY: 1000
Name IQ_LATESTK: 1000
Name IQ_LATESTQ: 500
Name IQ_LTM: 2000
Name IQ_LTMMONTH: 120000
Name IQ_MONTH: 15000
Name IQ_NTM: 6000
Name IQ_TODAY: 0
Name IQ_WEEK: 50000
Name IQ_YTD: 3000
Name IQ_YTDMONTH: 130000
Name Tax: [1]DCF!$D$44

Sheet Revenue Build & Growth Drivers
C2: ="Revenue Build & Growth Drivers For "&D5 -> Revenue Build & Growth Drivers For Keysight Technologies, Inc.
C3: $ in thousands except per unit
C5: Company Name | D5: Keysight Technologies, Inc.
C6: Ticker | D6: KEYS
C7: Valuation Date | D7: 45394
C8: Latest Adj. Closing Share Price Date | D8: 45393
C9: Latest Adj. Closing Share Price | D9: 160.14
C11: Revenue Projection | D11: Historical | G11: Projected
D12: ='Financial Statement Model'!D12 -> 44500 | E12: ='Financial Statement Model'!E12 -> 44865 | F12: ='Financial Statement Model'!F12 -> 45230 | G12: ='Financial Statement Model'!G12 -> 45596 | H12: ='Financial Statement Model'!H12 -> 45961 | I12: ='Financial Statement Model'!I12 -> 46326 | J12: ='Financial Statement Model'!J12 -> 46691 | K12: ='Financial Statement Model'!K12 -> 47057
C14: Total Revenues | D14: =+D23+D30 -> 4941000 | E14: =+E23+E30 -> 5420000 | F14: =+F23+F30 -> 5464000 | G14: =+G23+G30 -> 5740940 | H14: =+H23+H30 -> 6106477.8 | I14: =+I23+I30 -> 6500932.8 | J14: =+J23+J30 -> 6896456.2 | K14: =+K23+K30 -> 7322384.8
C15: % growth | E15: =+E14/D14-1 -> 0.096943938 | F15: =+F14/E14-1 -> 0.0081180812 | G15: =+G14/F14-1 -> 0.05068448 | H15: =+H14/G14-1 -> 0.063672116 | I15: =+I14/H14-1 -> 0.064596162 | J15: =+J14/I14-1 -> 0.060841011 | K15: =+K14/J14-1 -> 0.061760511
C17: Segmental Revenue Schedule | D17: Historical | G17: Projected
D18: ='Financial Statement Model'!D12 -> 44500 | E18: ='Financial Statement Model'!E12 -> 44865 | F18: ='Financial Statement Model'!F12 -> 45230 | G18: ='Financial Statement Model'!G12 -> 45596 | H18: ='Financial Statement Model'!H12 -> 45961 | I18: ='Financial Statement Model'!I12 -> 46326 | J18: ='Financial Statement Model'!J12 -> 46691 | K18: ='Financial Statement Model'!K12 -> 47057
C20: Communications Solutions Group (CSG)
C21: Aerospace, Defense & Government | D21: 1142000 | E21: 1171000 | F21: 1250000 | G21: =+F21*(1+G38) -> 1331250 | H21: =+G21*(1+H38) -> 1411125 | I21: =+H21*(1+I38) -> 1509903.8 | J21: =+I21*(1+J38) -> 1585398.9 | K21: =+J21*(1+K38) -> 1664668.9
C22: Commercial Communications | D22: 2381000 | E22: 2632000 | F22: 2435000 | G22: =+F22*(1+G39) -> 2435000 | H22: =+G22*(1+H39) -> 2483700 | I22: =+H22*(1+I39) -> 2558211 | J22: =+I22*(1+J39) -> 2634957.3 | K22: =+J22*(1+K39) -> 2714006
C23: Total CSG Revenue | D23: =SUM(D21:D22) -> 3523000 | E23: =SUM(E21:E22) -> 3803000 | F23: =SUM(F21:F22) -> 3685000 | G23: =SUM(G21:G22) -> 3766250 | H23: =SUM(H21:H22) -> 3894825 | I23: =SUM(I21:I22) -> 4068114.8 | J23: =SUM(J21:J22) -> 4220356.3 | K23: =SUM(K21:K22) -> 4378674.9
C24: % growth | E24: =+E23/D23-1 -> 0.079477718 | F24: =+F23/E23-1 -> -0.031028136 | G24: =+G23/F23-1 -> 0.022048847 | H24: =+H23/G23-1 -> 0.034138732 | I24: =+I23/H23-1 -> 0.044492307 | J24: =+J23/I23-1 -> 0.037423113 | K24: =+K23/J23-1 -> 0.037513105
C26: % of CSG Revenue
C27: =C21 -> Aerospace, Defense & Government | D27: =+D21/D$23 -> 0.32415555 | E27: =+E21/E$23 -> 0.3079148 | F27: =+F21/F$23 -> 0.33921303 | G27: =+G21/G$23 -> 0.3534683 | H27: =+H21/H$23 -> 0.36230768 | I27: =+I21/I$23 -> 0.37115564 | J27: =+J21/J$23 -> 0.37565524 | K27: =+K21/K$23 -> 0.3801764
C28: =C22 -> Commercial Communications | D28: =+D22/D$23 -> 0.67584445 | E28: =+E22/E$23 -> 0.6920852 | F28: =+F22/F$23 -> 0.66078697 | G28: =+G22/G$23 -> 0.6465317 | H28: =+H22/H$23 -> 0.63769232 | I28: =+I22/I$23 -> 0.62884436 | J28: =+J22/J$23 -> 0.62434476 | K28: =+K22/K$23 -> 0.6198236
C30: Electronic Industrial Solutions Group (EISG) | D30: 1418000 | E30: 1617000 | F30: 1779000 | G30: =+F30*(1+G40) -> 1974690 | H30: =+G30*(1+H40) -> 2211652.8 | I30: =+H30*(1+I40) -> 2432818.1 | J30: =+I30*(1+J40) -> 2676099.9 | K30: =+J30*(1+K40) -> 2943709.9
C31: % growth | E31: =+E30/D30-1 -> 0.1403385 | F31: =+F30/E30-1 -> 0.10018553 | G31: =+G30/F30-1 -> 0.11 | H31: =+H30/G30-1 -> 0.12 | I31: =+I30/H30-1 -> 0.1 | J31: =+J30/I30-1 -> 0.1 | K31: =+K30/J30-1 -> 0.1
C33: Growth Driver Assumptions
C35: Segment Revenue Growth Drivers | D35: Historical | G35: Projected
D36: ='Financial Statement Model'!D12 -> 44500 | E36: ='Financial Statement Model'!E12 -> 44865 | F36: ='Financial Statement Model'!F12 -> 45230 | G36: ='Financial Statement Model'!G12 -> 45596 | H36: ='Financial Statement Model'!H12 -> 45961 | I36: ='Financial Statement Model'!I12 -> 46326 | J36: ='Financial Statement Model'!J12 -> 46691 | K36: ='Financial Statement Model'!K12 -> 47057
C37: Revenue Growth Rate by Segment
C38: =+C21 -> Aerospace, Defense & Government | E38: =+E21/D21-1 -> 0.025394046 | F38: =+F21/E21-1 -> 0.067463706 | G38: 0.065 | H38: 0.06 | I38: 0.07 | J38: 0.05 | K38: 0.05
C39: =+C22 -> Commercial Communications | E39: =+E22/D22-1 -> 0.10541789 | F39: =+F22/E22-1 -> -0.074848024 | G39: 0 | H39: 0.02 | I39: 0.03 | J39: 0.03 | K39: 0.03
C40: =C30 -> Electronic Industrial Solutions Group (EISG) | E40: =+E30/D30-1 -> 0.1403385 | F40: =+F30/E30-1 -> 0.10018553 | G40: 0.11 | H40: 0.12 | I40: 0.1 | J40: 0.1 | K40: 0.1
C42: General Growth Drivers | D42: Historical | G42: Projected
D43: ='Financial Statement Model'!D12 -> 44500 | E43: ='Financial Statement Model'!E12 -> 44865 | F43: ='Financial Statement Model'!F12 -> 45230 | G43: ='Financial Statement Model'!G12 -> 45596 | H43: ='Financial Statement Model'!H12 -> 45961 | I43: ='Financial Statement Model'!I12 -> 46326 | J43: ='Financial Statement Model'!J12 -> 46691 | K43: ='Financial Statement Model'!K12 -> 47057
C44: Operating Expenses
C45: Gross Profit Margin | G45: 0.65 | H45: 0.65 | I45: 0.65 | J45: 0.65 | K45: 0.65
C46: SG&A % Revenue | G46: 0.38 | H46: 0.38 | I46: 0.38 | J46: 0.38 | K46: 0.38
C47: Other Operating Expense % of Revenue | G47: 0 | H47: 0 | I47: 0 | J47: 0 | K47: 0
C48: Days Sales Outstanding | G48: 60 | H48: 60 | I48: 60 | J48: 60 | K48: 60
C49: Inventory Turnover | G49: 1.5 | H49: 1.5 | I49: 1.5 | J49: 1.5 | K49: 1.5

Sheet Financial Statement Model
C2: ="Financial Statement Model For "&D5 -> Financial Statement Model For Keysight Technologies, Inc.
C3: $ in thousands except per share
C5: Company Name | D5: ='Revenue Build & Growth Drivers'!D5 -> Keysight Technologies, Inc. | G5: Circ toggle (1=on, 0=off) | J5: 1 | O5: Circ toggle: 1 = circularity on (interest based on average balances) Circ toggle: 0 = circularity off (interest income/expense set to zero)
C6: Ticker | D6: ='Revenue Build & Growth Drivers'!D6 -> KEYS
C7: Valuation Date | D7: ='Revenue Build & Growth Drivers'!D7 -> 45394
C8: Latest Adj. Closing Share Price Date | D8: ='Revenue Build & Growth Drivers'!D8 -> 45393
C9: Latest Adj. Closing Share Price | D9: ='Revenue Build & Growth Drivers'!D9 -> 160.14
C11: Income Statement | D11: Historical | G11: Projected | M11: 5 Year
D12: 44500 | E12: =EOMONTH(D12,12) -> 44865 | F12: =EOMONTH(E12,12) -> 45230 | G12: =EOMONTH(F12,12) -> 45596 | H12: =EOMONTH(G12,12) -> 45961 | I12: =EOMONTH(H12,12) -> 46326 | J12: =EOMONTH(I12,12) -> 46691 | K12: =EOMONTH(J12,12) -> 47057 | M12: CAGR
C14: Total Revenues | D14: 4941000 | E14: 5420000 | F14: 5464000 | G14: =+F14*(1+G34) -> 5740940 | H14: =+G14*(1+H34) -> 6106477.8 | I14: =+H14*(1+I34) -> 6500932.8 | J14: =+I14*(1+J34) -> 6896456.2 | K14: =+J14*(1+K34) -> 7322384.8 | M14: =+_xlfn.RRI(YEAR($K$12)-YEAR($F$12),F14,K14) -> 0.060299048
C15: Less: Cost of Sales | D15: 1873000 | E15: 1985000 | F15: 1945000
C16: Gross Profit | D16: 3068000 | E16: 3435000 | F16: 3519000
C17: SG&A Expense | D17: 1987000 | E17: 2099000 | F17: 2123000
C18: Other Operating Expense | D18: 0 | E18: 0 | F18: 0
C19: Operating Profit (EBIT) | D19: 1081000 | E19: 1336000 | F19: 1396000
C20: Nonoperating Income | D20: 27000 | E20: 62000 | F20: 143000 | O20: In the projected years, interest income is the only component of non-operating income
C21: Interest Expense | D21: 79000 | E21: 79000 | F21: 78000
C22: Unusual Expenses | D22: 19000 | E22: 34000 | F22: 104000 | O22: Set to zero
C23: Pre-tax Profit | D23: 1010000 | E23: 1285000 | F23: 1357000
C24: Income Taxes | D24: 116000 | E24: 161000 | F24: 300000
C25: Minority interest | D25: 0 | E25: 0 | F25: 0
C26: Net Income | D26: 894000 | E26: 1124000 | F26: 1057000
C28: Depreciation and Amortization | D28: 291000 | E28: 220000 | F28: 210000
C29: EBITDA | D29: 1372000 | E29: 1556000 | F29: 1606000
C31: Stock Compensation and Exercise of Options | D31: 103000 | E31: 125000 | F31: 135000 | O31: 3Y moving average
C33: Growth Rates and Margins
C34: Revenue Growth | E34: =+E14/D14-1 -> 0.096943938 | F34: =+F14/E14-1 -> 0.0081180812 | G34: =+'Revenue Build & Growth Drivers'!G15 -> 0.05068448 | H34: =+'Revenue Build & Growth Drivers'!H15 -> 0.063672116 | I34: =+'Revenue Build & Growth Drivers'!I15 -> 0.064596162 | J34: =+'Revenue Build & Growth Drivers'!J15 -> 0.060841011 | K34: =+'Revenue Build & Growth Drivers'!K15 -> 0.061760511
C35: Gross Profit Margin
C36: SG&A % of Revenue
C37: Other Operating Expense % of Revenue
C38: EBIT Margin
C39: EBITDA Margin
C40: Profit Margin
C41: Effective Tax Rate | O41: Keep the line flat at the 2023 level. If 2023 tax rate is negative, take average of the positive values and keep that constant for all the forecast years.
C43: Balance Sheet | D43: Historical | G43: Projected | M43: 5 Year
D44: =+D$12 -> 44500 | E44: =+E$12 -> 44865 | F44: =+F$12 -> 45230 | G44: =+G$12 -> 45596 | H44: =+H$12 -> 45961 | I44: =+I$12 -> 46326 | J44: =+J$12 -> 46691 | K44: =+K$12 -> 47057 | M44: CAGR
C46: Cash & Short-Term Investments | D46: 2052000 | E46: 2042000 | F46: 2472000
C47: Short-Term Receivables | D47: 735000 | E47: 905000 | F47: 900000
C48: Inventories | D48: 777000 | E48: 1057000 | F48: 1195000
C49: Other Current Assets | D49: 270000 | E49: 230000 | F49: 242000 | O49: Grows with Revenue
C50: Total Current Assets | D50: 3834000 | E50: 4234000 | F50: 4809000
C51: Net Property, Plant & Equipment | D51: 877000 | E51: 910000 | F51: 987000
C52: Total Long-Term Investments | D52: 134000 | E52: 210000 | F52: 97000 | O52: Grows with Revenue
C53: Intangible Assets | D53: 1900000 | E53: 1771000 | F53: 1795000
C54: Deferred Tax Assets | D54: 711000 | E54: 667000 | F54: 671000 | O54: Grows with Revenue
C55: Other Assets | D55: 325000 | E55: 306000 | F55: 324000 | O55: Grows with Revenue
C56: Total Assets | D56: 7781000 | E56: 8098000 | F56: 8683000
C58: ST Debt & Curr. Portion LT Debt | D58: 41000 | E58: 39000 | F58: 639000
C59: Accounts Payable | D59: 287000 | E59: 348000 | F59: 286000 | O59: Grows with Cost of Sales
C60: Income Tax Payable | D60: 74000 | E60: 96000 | F60: 90000 | O60: Set to zero
C61: Other Current Liabilities | D61: 907000 | E61: 924000 | F61: 1034000 | O61: Grows with Revenue
C62: Total Current Liabilities | D62: 1309000 | E62: 1407000 | F62: 2049000
C64: Long-Term Debt | D64: 1982000 | E64: 1979000 | F64: 1387000
C65: Provision for Risks & Charges | D65: 180000 | E65: 70000 | F65: 78000 | O65: Grows with Revenue
C66: Deferred Tax Liabilities | D66: 0 | E66: 0 | F66: 0 | O66: Grows with Revenue
C67: Other Liabilities | D67: 526000 | E67: 481000 | F67: 515000 | O67: Grows with Revenue
C68: Total Liabilities | D68: 3997000 | E68: 3937000 | F68: 4029000
C70: Total Shareholder's Equity | D70: 3784000 | E70: 4161000 | F70: 4654000 | O70: Include all items that could affect company's equity based on given structure.
C71: Total Equity | D71: 3784000 | E71: 4161000 | F71: 4654000 | O71: NCI should be linked directly to total equity.
C73: Total Liabilities and Equity | D73: 7781000 | E73: 8098000 | F73: 8683000
C75: Balance Check | D75: =+D56-D73 -> 0 | E75: =+E56-E73 -> 0 | F75: =+F56-F73 -> 0 | G75: =+G56-G73 -> 0 | H75: =+H56-H73 -> 0 | I75: =+I56-I73 -> 0 | J75: =+J56-J73 -> 0 | K75: =+K56-K73 -> 0
C77: Cash Flow Statement | D77: Historical | G77: Projected
D78: =+D$12 -> 44500 | E78: =+E$12 -> 44865 | F78: =+F$12 -> 45230 | G78: =+G$12 -> 45596 | H78: =+H$12 -> 45961 | I78: =+I$12 -> 46326 | J78: =+J$12 -> 46691 | K78: =+K$12 -> 47057
C80: Net Income | D80: 894000 | E80: 1124000 | F80: 1057000
C81: Depreciation, Depletion & Amortization | D81: 293000 | E81: 223000 | F81: 212000
C82: Deferred Taxes & Investment Tax Credit | D82: -53000 | E82: 7000 | F82: -3000
C83: Other Funds | D83: 152000 | E83: 194000 | F83: 161000
C84: Funds from Operations | D84: 1286000 | E84: 1548000 | F84: 1427000
C85: Changes in Working Capital | D85: 36000 | E85: -404000 | F85: -19000
C86: Cash Flow From Operating Activities | D86: 1322000 | E86: 1144000 | F86: 1408000
C88: Capital Expenditures | D88: -174000 | E88: -185000 | F88: -196000
C89: Net Assets from Acquisitions | D89: -178000 | E89: -33000 | F89: -85000 | O89: Set to zero (does not assume any specific future M&A activity for sake of forecast)
C90: Sale of Fixed Assets & Businesses | D90: 0 | E90: 0 | F90: 0 | O90: Set to zero (does not assume any sale for sake of forecast)
C91: Purchase/Sale of Investments | D91: 0 | E91: -33000 | F91: -7000
C92: Other Funds | D92: -1000 | E92: 0 | F92: 0 | O92: Set to zero
C93: Cash Flow From Investing Activities | D93: -353000 | E93: -251000 | F93: -288000
C95: Change in Capital Stock | D95: -614000 | E95: -786000 | F95: -635000 | O95: Set to zero
C96: Issuance/Reduction of Debt, Net | D96: 0 | E96: 0 | F96: 0
C97: Dividends | D97: 0 | E97: 0 | F97: 0
C98: Other Funds | D98: -57000 | E98: -75000 | F98: -52000 | O98: Set to zero
C99: Cash Flow From Financing Activities | D99: -671000 | E99: -861000 | F99: -687000
C101: Effect of Exchange Rate on Cash and Equivalents | D101: 3000 | E101: -43000 | F101: -2000 | O101: Set to zero
C103: Net Change in Cash During Period | D103: 301000 | E103: -11000 | F103: 431000
C105: Line Item Schedules
C107: Current Assets Schedule | D107: Historical | G107: Projected
D108: =+D$12 -> 44500 | E108: =+E$12 -> 44865 | F108: =+F$12 -> 45230 | G108: =+G$12 -> 45596 | H108: =+H$12 -> 45961 | I108: =+I$12 -> 46326 | J108: =+J$12 -> 46691 | K108: =+K$12 -> 47057
C110: Accounts Receivable
C111: Beginning of Period
C112: Increase (Decrease)
C113: End of Period
C115: A/R Forecasting Approach (1=Rev Growth, 2=DSO) | E115: 1
C117: Revenue Growth Rate (Approach 1)
C118: Days Sales Outstanding (Approach 2) | O118: For historical period, calculate using year end balance of accounts receivable and assume 365 days in a year
C119: Revenue
C121: Inventories
C122: Beginning of Period
C123: Increase (Decrease)
C124: End of Period
C126: Inventory Forecasting Approach (1=Cost of Sales Growth, 2=Turnover) | E126: 1
C128: Cost of Sales Growth Rate (Approach 1)
...

Sheet Integrated DCF Model
C2: ="Discounted Cash Flow Model For "&D5 -> Discounted Cash Flow Model For Keysight Technologies, Inc.
C3: $ in thousands except per share | J3: Values
C5: Company Name | D5: ='Revenue Build & Growth Drivers'!D5 -> Keysight Technologies, Inc. | G5: Basic Shares Outstanding | J5: =+D66 -> 175044.6
C6: Ticker | D6: ='Revenue Build & Growth Drivers'!D6 -> KEYS | G6: Fully Diluted Shares Outstanding | J6: =+D71 -> 178193.6
C7: Valuation Date | D7: ='Revenue Build & Growth Drivers'!D7 -> 45394 | G7: Discount Rate (WACC) | J7: =+'WACC Build'!D45 -> 0
C8: Latest Adj. Closing Share Price Date | D8: ='Revenue Build & Growth Drivers'!D8 -> 45393 | G8: Midyear Adjustment (1=on, 0=off) | J8: 0
C9: Latest Adj. Closing Share Price | D9: ='Revenue Build & Growth Drivers'!D9 -> 160.14
C11: Unlevered Free Cash Flow | E11: Historical | H11: Projected | N11: 5 Year
E12: ='Financial Statement Model'!D12 -> 44500 | F12: ='Financial Statement Model'!E12 -> 44865 | G12: ='Financial Statement Model'!F12 -> 45230 | H12: ='Financial Statement Model'!G12 -> 45596 | I12: ='Financial Statement Model'!H12 -> 45961 | J12: ='Financial Statement Model'!I12 -> 46326 | K12: ='Financial Statement Model'!J12 -> 46691 | L12: ='Financial Statement Model'!K12 -> 47057 | N12: CAGR
C14: Total Revenues
C15: YoY Growth Rate (%)
C17: Gross Profit
C18: Gross Margin (%)
C20: EBITDA
C21: EBITDA Margin (%)
C23: Operating Profit (EBIT)
C24: EBIT Margin (%)
C26: Tax on EBIT
C27: Tax Rate (%)
C29: NOPAT/EBIAT
C31: Plus: Depreciation and Amortization
... C36: Unlevered Free Cash Flow (UFCF)
C38: Net Working Capital Schedule | E38: Historical | H38: Projected
E39: ='Financial Statement Model'!D12 -> 44500 | F39: ='Financial Statement Model'!E12 -> 44865 | G39: ='Financial Statement Model'!F12 -> 45230 | H39: ='Financial Statement Model'!G12 -> 45596 | I39: ='Financial Statement Model'!H12 -> 45961 | J39: ='Financial Statement Model'!I12 -> 46326 | K39: ='Financial Statement Model'!J12 -> 46691 | L39: ='Financial Statement Model'!K12 -> 47057
C41: Short-Term Receivables
C42: Inventories
C43: Other Current Assets
C44: Current Assets (Ex. Cash)
C46: Accounts Payable
C47: Other Current Liabilities
C48: Current Liabilities
C50: Net Working Capital
C52: Change in Net Working Capital
C54: ="Present Value of UFCFs as of "&TEXT(D7,("mmm dd, yyyy")) -> Present Value of UFCFs as of Apr 12, 2024 | F54: Stub % | H54: Stub Year | I54: Year 2 | J54: Year 3 | K54: Year 4 | L54: Year 5
C55: Dates for Discounting UFCF
C57: Periods for Discounting UFCF | P57: Use Actual/Actual convention for Periods and Stub %
C59: Stub-adjusted Unlevered Free Cash Flow (UFCF) | P59: Factor in Y1 UFCF for the Stub Rate
C61: PV of Stub-adjusted UFCFs
C63: Basic to Fully Diluted Shares Bridge (in 000s)
C66: Basic Shares | D66: 175044.6
C67: Restricted Stock | D67: 2149
C68: Options/Warrants | D68: 1000
C69: Convertible Debt | D69: 0
C70: Convertible Preferred Stock | D70: 0
C71: Fully Diluted Shares Outstanding | D71: =SUM(D66:D70) -> 178193.6
C73: Terminal Value and Equity Value Bridge
C76: Terminal Value - Multiples Method | H76: Terminal Value - Perpetual Growth Method
C78: EV/EBITDA | E78: 22 | H78: Terminal UFCF Growth Rate | L78: 0.06
C80: Implied Terminal Value | H80: Implied Terminal Value
C81: Implied Terminal UFCF Growth Rate | H81: Implied Terminal EV/EBITDA
C83: Plus: PV of Terminal Value | H83: Plus: PV of Terminal Value
C84: Plus: Sum of PV of Stub-adjusted UFCFs | H84: Plus: Sum of PV of Stub-adjusted UFCFs
C85: Implied Enterprise Value | H85: Implied Enterprise Value
C87: % of Implied EV from Terminal Value | H87: % of Implied EV from Terminal Value
C89: Plus: Cash and Cash Equivalents | H89: Plus: Cash and Cash Equivalents
C90: Less: Debt & Capital Leases (excl. Operating Leases) | H90: Less: Debt & Capital Leases (excl. Operating Leases)
C91: Less: Preferred Stock | H91: Less: Preferred Stock
C92: Less: Non-controlling Interest | H92: Less: Non-controlling Interest
C93: Implied Equity Value | H93: Implied Equity Value
C95: Implied Share Price | H95: Implied Share Price
... C101: EV / EBIT | H101: EV / EBIT
C103: Data Tables and Football Field
E106: EV/EBITDA Multiple
D107: Discount Rate (WACC) | P107: Instructions: To complete the sensitivity tables, enter the calculated WACC in cells E111 and E121. Then, for the remaining rows, sequentially add/subtract 0.5% to generate the different scenarios. Enter the terminal EBITDA multiple in cell I107 and for the remaining columns, sequentially add/subtract 0.5x to generate the alternative scenarios. For Terminal UFCF Growth Rate, enter the terminal growth rate in cell I117 and for the remaining columns, sequentially add/subtract 0.5% to generate the alternative scenarios.
E116: Terminal UFCF Growth Rate
D117: Discount Rate (WACC)

Sheet WACC Build
C2: ="WACC Build For "&D5 -> WACC Build For Keysight Technologies, Inc.
C3: $ in thousands except per share | J3: Values
C5: Company Name | D5: ='Revenue Build & Growth Drivers'!D5 -> Keysight Technologies, Inc. | G5: Basic Shares Outstanding | J5: =+'Integrated DCF Model'!D66 -> 175044.6
C6: Ticker | D6: ='Revenue Build & Growth Drivers'!D6 -> KEYS | G6: Fully Diluted Shares Outstanding | J6: =+'Integrated DCF Model'!D71 -> 178193.6
C7: Valuation Date | D7: ='Revenue Build & Growth Drivers'!D7 -> 45394
C8: Latest Adj. Closing Share Price Date | D8: ='Revenue Build & Growth Drivers'!D8 -> 45393
C9: Latest Adj. Closing Share Price | D9: ='Revenue Build & Growth Drivers'!D9 -> 160.14
C11: Cost of Debt Calculation | F11: Beta (β) Calculator
C14: Interest on Short-term Bank Credit | F14: =D5&" ("&D6&")" -> Keysight Technologies, Inc. (KEYS) | J14: S&P 500 Index | N14: Exclude operating leases from cost of debt and capital structure weight calculations.
C15: Interest on Long-term Debt | F15: Date | G15: Adj. Close Price | H15: Return (%) | J15: Date | K15: Adj. Close Price | L15: Return (%)
C16: Total Interest Expenses | F16: 44317 | G16: 142.38001 | J16: 44317 | K16: 4204.1099
F17: 44348 | G17: 154.41 | H17: =+G17/G16-1 -> 0.084492194 | J17: 44348 | K17: 4297.5 | L17: =+K17/K16-1 -> 0.02221401
C18: Short-term Bank Credit/Revolver | F18: 44378 | G18: 164.55 | H18: =+G18/G17-1 -> 0.065669314 | J18: 44378 | K18: 4395.2598 | L18: =+K18/K17-1 -> 0.022748055
C19: Current Portion of LT Debt & Finance leases | F19: 44409 | G19: 179.38001 | H19: =+G19/G18-1 -> 0.090124593 | J19: 44409 | K19: 4522.6802 | L19: =+K19/K18-1 -> 0.028990416
C20: LT Debt & Finance leases (Ex. Current Portion) | F20: 44440 | G20: 164.28999 | H20: =+G20/G19-1 -> -0.084123155 | J20: 44440 | K20: 4307.54 | L20: =+K20/K19-1 -> -0.047569169
C21: Total Debt | F21: 44470 | G21: 180.02 | H21: =+G21/G20-1 -> 0.095745399 | J21: 44470 | K21: 4605.3799 | L21: =+K21/K20-1 -> 0.069143836
F22: 44501 | G22: 194.48 | H22: =+G22/G21-1 -> 0.080324362 | J22: 44501 | K22: 4567 | L22: =+K22/K21-1 -> -0.0083337062
C23: Pre-tax Cost of Debt | F23: 44531 | G23: 206.51 | H23: =+G23/G22-1 -> 0.061857257 | J23: 44531 | K23: 4766.1802 | L23: =+K23/K22-1 -> 0.043612914
C24: Effective Tax Rate | F24: 44562 | G24: 168.82001 | H24: =+G24/G23-1 -> -0.18250927 | J24: 44562 | K24: 4515.5498 | L24: =+K24/K23-1 -> -0.052585165 | N24: Use 2023 effective tax rate. If negative, take average of the positive values from historical periods.
F25: 44593 | G25: 157.36999 | H25: =+G25/G24-1 -> -0.067823786 | J25: 44593 | K25: 4373.9399 | L25: =+K25/K24-1 -> -0.031360492
C26: Effective Cost of Debt | F26: 44621 | G26: 157.97 | H26: =+G26/G25-1 -> 0.003812709 | J26: 44621 | K26: 4530.4102 | L26: =+K26/K25-1 -> 0.035773288
F27: 44652 | G27: 140.27 | H27: =+G27/G26-1 -> -0.11204657 | J27: 44652 | K27: 4131.9302 | L27: =+K27/K26-1 -> -0.087956712
C28: Cost of Equity Calculation | F28: 44682 | G28: 145.60001 | H28: =+G28/G27-1 -> 0.03799816 | J28: 44682 | K28: 4132.1499 | L28: =+K28/K27-1 -> 5.3177569e-05
F29: 44713 | G29: 137.85001 | H29: =+G29/G28-1 -> -0.05322802 | J29: 44713 | K29: 3785.3799 | L29: =+K29/K28-1 -> -0.08392
F30: 44743 | G30: 162.60001 | H30: =+G30/G29-1 -> 0.17954297 | J30: 44743 | K30: 4130.29 | L30: =+K30/K29-1 -> 0.091116392
C31: Equity Risk Premium | D31: 0.055 | F31: 44774 | G31: 163.89 | H31: =+G31/G30-1 -> 0.007933536 | J31: 44774 | K31: 3955 | L31: =+K31/K30-1 -> -0.042440128
C32: Risk-free Rate | D32: 0.0456 | F32: 44805 | G32: 157.36 | H32: =+G32/G31-1 -> -0.039843786 | J32: 44805 | K32: 3585.6201 | L32: =+K32/K31-1 -> -0.093395672
C33: Company Beta | D33: =+L52 -> 1.1969956 | F33: 44835 | G33: 174.14999 | H33: =+G33/G32-1 -> 0.10669797 | J33: 44835 | K33: 3871.98 | L33: =+K33/K32-1 -> 0.079863414
F34: 44866 | G34: 180.89 | H34: =+G34/G33-1 -> 0.038702298 | J34: 44866 | K34: 4080.1101 | L34: =+K34/K33-1 -> 0.053752893
C35: Cost of Equity | D35: =+D32+D33*D31 -> 0.11143476 | F35: 44896 | G35: 171.07001 | H35: =+G35/G34-1 -> -0.054287092 | J35: 44896 | K35: 3839.5 | L35: =+K35/K34-1 -> -0.058971474
F36: 44927 | G36: 179.35001 | H36: =+G36/G35-1 -> 0.048401231 | J36: 44927 | K36: 4076.6001 | L36: =+K36/K35-1 -> 0.061752858
C37: Capital Structure and WACC | F37: 44958 | G37: 159.96001 | H37: =+G37/G36-1 -> -0.10811262 | J37: 44958 | K37: 3970.1499 | L37: =+K37/K36-1 -> -0.026112494
F38: 44986 | G38: 161.48 | H38: =+G38/G37-1 -> 0.0095023064 | J38: 44986 | K38: 4109.3101 | L38: =+K38/K37-1 -> 0.035051613
F39: 45017 | G39: 144.64 | H39: =+G39/G38-1 -> -0.10428534 | J39: 45017 | K39: 4169.48 | L39: =+K39/K38-1 -> 0.014642341
C40: Total Debt | F40: 45047 | G40: 161.8 | H40: =+G40/G39-1 -> 0.11863941 | J40: 45047 | K40: 4179.8301 | L40: =+K40/K39-1 -> 0.0024823475
C41: % of Total Capital | F41: 45078 | G41: 167.45 | H41: =+G41/G40-1 -> 0.034919616 | J41: 45078 | K41: 4450.3799 | L41: =+K41/K40-1 -> 0.064727465
C42: Equity Value | F42: 45108 | G42: 161.08 | H42: =+G42/G41-1 -> -0.038041177 | J42: 45108 | K42: 4588.96 | L42: =+K42/K41-1 -> 0.031138932
C43: % of Total Capital | F43: 45139 | G43: 133.3 | H43: =+G43/G42-1 -> -0.17246088 | J43: 45139 | K43: 4507.6602 | L43: =+K43/K42-1 -> -0.01771639
F44: 45170 | G44: 132.31 | H44: =+G44/G43-1 -> -0.0074268941 | J44: 45170 | K44: 4288.0498 | L44: =+K44/K43-1 -> -0.048719367
C45: Weighted Average Cost of Capital (WACC) | F45: 45200 | G45: 122.05 | H45: =+G45/G44-1 -> -0.077545122 | J45: 45200 | K45: 4193.7998 | L45: =+K45/K44-1 -> -0.021979689
F46: 45231 | G46: 135.89 | H46: =+G46/G45-1 -> 0.11339611 | J46: 45231 | K46: 4567.7998 | L46: =+K46/K45-1 -> 0.089179269
F47: 45261 | G47: 159.09 | H47: =+G47/G46-1 -> 0.1707263 | J47: 45261 | K47: 4769.8301 | L47: =+K47/K46-1 -> 0.044229231
F48: 45292 | G48: 153.26 | H48: =+G48/G47-1 -> -0.036645931 | J48: 45292 | K48: 4845.6499 | L48: =+K48/K47-1 -> 0.015895708
F49: 45323 | G49: 154.3 | H49: =+G49/G48-1 -> 0.0067859065 | J49: 45323 | K49: 5096.27 | L49: =+K49/K48-1 -> 0.051720641
F50: 45352 | G50: 156.38001 | H50: =+G50/G49-1 -> 0.013480246 | J50: 45352 | K50: 5254.3501 | L50: =+K50/K49-1 -> 0.03101878
F51: 45383 | G51: 147.94 | H51: =+G51/G50-1 -> -0.053971114 | J51: 45383 | K51: 5035.6899 | L51: =+K51/K50-1 -> -0.041615072
K52: Company Beta (3Y Monthly) >> | L52: =+SLOPE(H17:H51,L17:L51) -> 1.1969956
