Workbook
Name Discount_Rate: 'Integrated DCF Model'!$E$10
Name Discount_Rate: #REF!
Name IQ_CH: 110000
Name IQ_CQ: 5000
Name IQ_CY: 10000
Name IQ_DAILY: 500000
Name IQ_FH: 100000
Name IQ_FQ: 500
Name IQ_FWD_CY: 10001
Name IQ_FWD_CY1: 10002
Name IQ_FWD_CY2: 10003
Name IQ_FWD_FY: 1001
Name IQ_FWD_FY1: 1002
Name IQ_FWD_FY2: 1003
Name IQ_FWD_Q: 501
Name IQ_FWD_Q1: 502
Name IQ_FWD_Q2: 503
Name IQ_FY: 1000
Name IQ_LATESTK: 1000
Name IQ_LATESTQ: 500
Name IQ_LTM: 2000
Name IQ_LTMMONTH: 120000
Name IQ_MONTH: 15000
Name IQ_NTM: 6000
Name IQ_TODAY: 0
Name IQ_WEEK: 50000
Name IQ_YTD: 3000
Name IQ_YTDMONTH: 130000
Name Tax: [1]DCF!$D$44

Sheet Revenue Build & Growth Drivers
C2: ="Revenue Build & Growth Drivers For "&D5 -> Revenue Build & Growth Drivers For TopBuild Corp.
C3: $ in thousands except per unit
C5: Company Name | D5: TopBuild Corp.
C6: Ticker | D6: BLD
C7: Valuation Date | D7: 45394
C8: Latest Adj. Closing Share Price Date | D8: 45393
C9: Latest Adj. Closing Share Price | D9: 421.45
C11: Revenue Projection | D11: Historical | G11: Projected
D12: ='Financial Statement Model'!D12 -> 44561 | E12: ='Financial Statement Model'!E12 -> 44926 | F12: ='Financial Statement Model'!F12 -> 45291 | G12: ='Financial Statement Model'!G12 -> 45657 | H12: ='Financial Statement Model'!H12 -> 46022 | I12: ='Financial Statement Model'!I12 -> 46387 | J12: ='Financial Statement Model'!J12 -> 46752 | K12: ='Financial Statement Model'!K12 -> 47118
C14: Total Revenues | D14: =+D20+D23-D26 -> 3486207 | E14: =+E20+E23-E26 -> 5008744 | F14: =+F20+F23-F26 -> 5194694 | G14: =+G20+G23-G26 -> 5387941.2 | H14: =+H20+H23-H26 -> 5546043.1 | I14: =+I20+I23-I26 -> 5726018.4 | J14: =+J20+J23-J26 -> 5949773.4 | K14: =+K20+K23-K26 -> 6205869.8
C15: % growth | E15: =+E14/D14-1 -> 0.43673167 | F15: =+F14/E14-1 -> 0.037125076 | G15: =+G14/F14-1 -> 0.037200876 | H15: =+H14/G14-1 -> 0.029343659 | I15: =+I14/H14-1 -> 0.032451131 | J15: =+J14/I14-1 -> 0.039076893 | K15: =+K14/J14-1 -> 0.043043048
C17: Segmental Revenue Schedule | D17: Historical | G17: Projected
D18: ='Financial Statement Model'!D12 -> 44561 | E18: ='Financial Statement Model'!E12 -> 44926 | F18: ='Financial Statement Model'!F12 -> 45291 | G18: ='Financial Statement Model'!G12 -> 45657 | H18: ='Financial Statement Model'!H12 -> 46022 | I18: ='Financial Statement Model'!I12 -> 46387 | J18: ='Financial Statement Model'!J12 -> 46752 | K18: ='Financial Statement Model'!K12 -> 47118
C20: Installation Revenue | D20: 2378401 | E20: 2969978 | F20: 3188232 | G20: =+F20*(1+G21) -> 3331702.4 | H20: =+G20*(1+H21) -> 3448312 | I20: =+H20*(1+I21) -> 3569002.9 | J20: =+I20*(1+J21) -> 3729608.1 | K20: =+J20*(1+K21) -> 3897440.4
C21: % growth | E21: =+E20/D20-1 -> 0.24872887 | F21: =+F20/E20-1 -> 0.07348674 | G21: =+SUM(G34:G36) -> 0.045 | H21: =+SUM(H34:H36) -> 0.035 | I21: =+SUM(I34:I36) -> 0.035 | J21: =+SUM(J34:J36) -> 0.045 | K21: =+SUM(K34:K36) -> 0.045
C23: Specialty Distribution | D23: 1287176 | E23: 2278261 | F23: 2268339 | G23: =+F23*(1+G24) -> 2325047.5 | H23: =+G23*(1+H24) -> 2371548.4 | I23: =+H23*(1+I24) -> 2442694.9 | J23: =+I23*(1+J24) -> 2515975.7 | K23: =+J23*(1+K24) -> 2616614.8
C24: % growth | E24: =+E23/D23-1 -> 0.76996852 | F24: =+F23/E23-1 -> -0.0043550761 | G24: =+SUM(G39:G41) -> 0.025 | H24: =+SUM(H39:H41) -> 0.02 | I24: =+SUM(I39:I41) -> 0.03 | J24: =+SUM(J39:J41) -> 0.03 | K24: =+SUM(K39:K41) -> 0.04
C26: Intercompany Eliminations | D26: 179370 | E26: 239495 | F26: 261877 | G26: =+G27*(G23+G20) -> 268808.75 | H26: =+H27*(H23+H20) -> 273817.38 | I26: =+I27*(I23+I20) -> 285679.38 | J26: =+J27*(J23+J20) -> 295810.35 | K26: =+K27*(K23+K20) -> 308185.36
C27: Eliminations as % of Gross Revenue | D27: =+D26/(D23+D20) -> 0.048933633 | E27: =+E26/(E23+E20) -> 0.045633402 | F27: =+F26/(F23+F20) -> 0.047992961 | G27: =+AVERAGE(D27:F27) -> 0.047519999 | H27: =+AVERAGE(E27:G27) -> 0.047048787 | I27: =+AVERAGE(F27:H27) -> 0.047520582 | J27: =+AVERAGE(G27:I27) -> 0.047363123 | K27: =+AVERAGE(H27:J27) -> 0.047310831
C29: Growth Driver Assumptions
C31: Segment Revenue Growth Drivers | D31: Historical | G31: Projected
D32: ='Financial Statement Model'!D12 -> 44561 | E32: ='Financial Statement Model'!E12 -> 44926 | F32: ='Financial Statement Model'!F12 -> 45291 | G32: ='Financial Statement Model'!G12 -> 45657 | H32: ='Financial Statement Model'!H12 -> 46022 | I32: ='Financial Statement Model'!I12 -> 46387 | J32: ='Financial Statement Model'!J12 -> 46752 | K32: ='Financial Statement Model'!K12 -> 47118
C33: % growth attribution for Installation segment
C34: Selling prices | E34: 0.122 | F34: 0.036 | G34: 0.015 | H34: 0.005 | I34: 0.005 | J34: 0.005 | K34: 0.005
C35: Volumes | E35: 0.092 | F35: 0 | G35: -0.005 | H35: -0.005 | I35: 0 | J35: 0.01 | K35: 0.01
C36: Acquisitions | E36: 0.034 | F36: 0.036 | G36: 0.035 | H36: 0.035 | I36: 0.03 | J36: 0.03 | K36: 0.03
C38: % growth attribution for Specialty Distribution segment
C39: Selling prices | E39: 0.158 | F39: 0.011 | G39: 0.015 | H39: 0.005 | I39: 0.005 | J39: 0.005 | K39: 0.005
C40: Volumes | E40: -0.006 | F40: -0.016 | G40: -0.005 | H40: 0 | I40: 0.01 | J40: 0.01 | K40: 0.02
C41: Acquisitions | E41: 0.618 | F41: 0 | G41: 0.015 | H41: 0.015 | I41: 0.015 | J41: 0.015 | K41: 0.015
C43: General Growth Drivers | D43: Historical | G43: Projected
D44: ='Financial Statement Model'!D12 -> 44561 | E44: ='Financial Statement Model'!E12 -> 44926 | F44: ='Financial Statement Model'!F12 -> 45291 | G44: ='Financial Statement Model'!G12 -> 45657 | H44: ='Financial Statement Model'!H12 -> 46022 | I44: ='Financial Statement Model'!I12 -> 46387 | J44: ='Financial Statement Model'!J12 -> 46752 | K44: ='Financial Statement Model'!K12 -> 47118
C45: Operating Expenses
C46: Gross Profit Margin | D46: ='Financial Statement Model'!D35 -> 0.27949832 | E46: ='Financial Statement Model'!E35 -> 0.29682471 | F46: ='Financial Statement Model'!F35 -> 0.30874196 | G46: 0.31 | H46: 0.315 | I46: 0.317 | J46: 0.319 | K46: 0.321
C47: SG&A % Revenue | D47: ='Financial Statement Model'!D36 -> 0.13828697 | E47: ='Financial Statement Model'!E36 -> 0.1374107 | F47: ='Financial Statement Model'!F36 -> 0.13644596 | G47: 0.135 | H47: 0.135 | I47: 0.135 | J47: 0.135 | K47: 0.135
C48: Other Operating Expense % of Revenue | D48: ='Financial Statement Model'!D37 -> 0 | E48: ='Financial Statement Model'!E37 -> 0 | F48: ='Financial Statement Model'!F37 -> 0 | G48: 0 | H48: 0 | I48: 0 | J48: 0 | K48: 0
C49: Days Sales Outstanding | D49: ='Financial Statement Model'!D118 -> 69.982343 | E49: ='Financial Statement Model'!E118 -> 60.926635 | F49: ='Financial Statement Model'!F118 -> 56.141572 | G49: 55 | H49: 55 | I49: 55 | J49: 55 | K49: 55
C50: Inventory Turnover | E50: ='Financial Statement Model'!E129 -> 8.0293473 | F50: ='Financial Statement Model'!F129 -> 9.8452668 | G50: 10 | H50: 10 | I50: 10 | J50: 10 | K50: 10
C51: Days Payables Outstanding | D51: =+'Financial Statement Model'!D145 -> 67.12258 | E51: =+'Financial Statement Model'!E145 -> 50.481359 | F51: =+'Financial Statement Model'!F145 -> 47.731701 | G51: 50 | H51: 50 | I51: 50 | J51: 50 | K51: 50
C53: Acquisition spend allocation to:
C54: Goodwill | G54: 0.5 | H54: 0.5 | I54: 0.5 | J54: 0.5 | K54: 0.5
C55: Intangibles | G55: 0.3 | H55: 0.3 | I55: 0.3 | J55: 0.3 | K55: 0.3
C56: PPE | G56: 0.2 | H56: 0.2 | I56: 0.2 | J56: 0.2 | K56: 0.2

Sheet Financial Statement Model
C2: ="Financial Statement Model For "&D5 -> Financial Statement Model For TopBuild Corp.
C3: $ in thousands except per share
C5: Company Name | D5: ='Revenue Build & Growth Drivers'!D5 -> TopBuild Corp. | G5: Circ toggle (1=on, 0=off) | J5: 1
C6: Ticker | D6: ='Revenue Build & Growth Drivers'!D6 -> BLD
C7: Valuation Date | D7: ='Revenue Build & Growth Drivers'!D7 -> 45394
C8: Latest Adj. Closing Share Price Date | D8: ='Revenue Build & Growth Drivers'!D8 -> 45393
C9: Latest Adj. Closing Share Price | D9: ='Revenue Build & Growth Drivers'!D9 -> 421.45
C11: Income Statement | D11: Historical | G11: Projected | M11: 5 Year
D12: 44561 | E12: =EOMONTH(D12,12) -> 44926 | F12: =EOMONTH(E12,12) -> 45291 | G12: =EOMONTH(F12,12) -> 45657 | H12: =EOMONTH(G12,12) -> 46022 | I12: =EOMONTH(H12,12) -> 46387 | J12: =EOMONTH(I12,12) -> 46752 | K12: =EOMONTH(J12,12) -> 47118 | M12: CAGR
C14: Total Revenues | D14: 3486207 | E14: 5008744 | F14: 5194694 | G14: =+F14*(1+G34) -> 5387941.2 | H14: =+G14*(1+H34) -> 5546043.1 | I14: =+H14*(1+I34) -> 5726018.4 | J14: =+I14*(1+J34) -> 5949773.4 | K14: =+J14*(1+K34) -> 6205869.8 | M14: =+_xlfn.RRI(YEAR($K$12)-YEAR($F$12),F14,K14) -> 0.036211812
C15: Less: Cost of Sales | D15: 2511818 | E15: 3522025 | F15: 3590874 | G15: =+G14-G16 -> 3717679.4 | H15: =+H14-H16 -> 3799039.5 | I15: =+I14-I16 -> 3910870.6 | J15: =+J14-J16 -> 4051795.7 | K15: =+K14-K16 -> 4213785.6
C16: Gross Profit | D16: 974389 | E16: 1486719 | F16: 1603820 | G16: =+G14*G35 -> 1670261.8 | H16: =+H14*H35 -> 1747003.6 | I16: =+I14*I35 -> 1815147.8 | J16: =+J14*J35 -> 1897977.7 | K16: =+K14*K35 -> 1992084.2 | M16: =+_xlfn.RRI(YEAR($K$12)-YEAR($F$12),F16,K16) -> 0.04431235
C17: SG&A Expense | D17: 482097 | E17: 688255 | F17: 708795 | G17: =+G14*G36 -> 727372.06 | H17: =+H14*H36 -> 748715.81 | I17: =+I14*I36 -> 773012.49 | J17: =+J14*J36 -> 803219.42 | K17: =+K14*K36 -> 837792.43
C18: Other Operating Expense | D18: 0 | E18: 0 | F18: 0 | G18: =+G37*G14 -> 0 | H18: =+H37*H14 -> 0 | I18: =+I37*I14 -> 0 | J18: =+J37*J14 -> 0 | K18: =+K37*K14 -> 0
C19: Operating Profit (EBIT) | D19: 492292 | E19: 798464 | F19: 895025 | G19: =+G16-G17-G18 -> 942889.7 | H19: =+H16-H17-H18 -> 998287.75 | I19: =+I16-I17-I18 -> 1042135.4 | J19: =+J16-J17-J18 -> 1094758.3 | K19: =+K16-K17-K18 -> 1154291.8 | M19: =+_xlfn.RRI(YEAR($K$12)-YEAR($F$12),F19,K19) -> 0.052194647
C20: Nonoperating Income | D20: -1352 | E20: 1687 | F20: 21272 | G20: =G279 -> 32706.465 | H20: =H279 -> 48004.033 | I20: =I279 -> 59038.984 | J20: =J279 -> 72381.696 | K20: =K279 -> 93958.827
C21: Interest Expense | D21: 29143 | E21: 56716 | F21: 74614 | G21: =G260+G274+G285 -> 71175.751 | H21: =H260+H274+H285 -> 68116.69 | I21: =I260+I274+I285 -> 52375.987 | J21: =J260+J274+J285 -> 38210.987 | K21: =K260+K274+K285 -> 38218.861
C22: Unusual Expenses | D22: 28354 | E22: 1300 | F22: 16200 | G22: 0 | H22: 0 | I22: 0 | J22: 0 | K22: 0
C23: Pre-tax Profit | D23: 433443 | E23: 742135 | F23: 825483 | G23: =+G19+G20-G21-G22 -> 904420.42 | H23: =+H19+H20-H21-H22 -> 978175.1 | I23: =+I19+I20-I21-I22 -> 1048798.4 | J23: =+J19+J20-J21-J22 -> 1128929 | K23: =+K19+K20-K21-K22 -> 1210031.8 | M23: =+_xlfn.RRI(YEAR($K$12)-YEAR($F$12),F23,K23) -> 0.079487771
C24: Income Taxes | D24: 109427 | E24: 186146 | F24: 211229 | G24: =+G23*G41 -> 231427.93 | H24: =+H23*H41 -> 250300.67 | I24: =+I23*I41 -> 268372.13 | J24: =+J23*J41 -> 288876.39 | K24: =+K23*K41 -> 309629.39
C25: Minority interest | D25: 0 | E25: 0 | F25: 0 | G25: =G225 -> 0 | H25: =H225 -> 0 | I25: =I225 -> 0 | J25: =J225 -> 0 | K25: =K225 -> 0
C26: Net Income | D26: 324016 | E26: 555989 | F26: 614254 | G26: =+G23-G24-G25 -> 672992.49 | H26: =+H23-H24-H25 -> 727874.43 | I26: =+I23-I24-I25 -> 780426.23 | J26: =+J23-J24-J25 -> 840052.63 | K26: =+K23-K24-K25 -> 900402.37 | M26: =+_xlfn.RRI(YEAR($K$12)-YEAR($F$12),F26,K26) -> 0.079487771
C28: Depreciation and Amortization | D28: 79390 | E28: 123335 | F28: 132878 | G28: =+G183+G160+G302 -> 117580.75 | H28: =+H183+H160+H302 -> 138036.58 | I28: =+I183+I160+I302 -> 159617.58 | J28: =+J183+J160+J302 -> 181671.05 | K28: =+K183+K160+K302 -> 205964.72
C29: EBITDA | D29: 571682 | E29: 921799 | F29: 1027903 | G29: =+G19+G28 -> 1060470.5 | H29: =+H19+H28 -> 1136324.3 | I29: =+I19+I28 -> 1201752.9 | J29: =+J19+J28 -> 1276429.4 | K29: =+K19+K28 -> 1360256.5 | M29: =+_xlfn.RRI(YEAR($K$12)-YEAR($F$12),F29,K29) -> 0.057629939
C31: Stock Compensation and Exercise of Options | D31: 11316 | E31: 12310 | F31: 15838 | G31: =+AVERAGE(D31:F31) -> 13154.667 | H31: =+AVERAGE(E31:G31) -> 13767.556 | I31: =+AVERAGE(F31:H31) -> 14253.407 | J31: =+AVERAGE(G31:I31) -> 13725.21 | K31: =+AVERAGE(H31:J31) -> 13915.391
C33: Growth Rates and Margins
C34: Revenue Growth | E34: =+E14/D14-1 -> 0.43673167 | F34: =+F14/E14-1 -> 0.037125076 | G34: =+'Revenue Build & Growth Drivers'!G15 -> 0.037200876 | H34: =+'Revenue Build & Growth Drivers'!H15 -> 0.029343659 | I34: =+'Revenue Build & Growth Drivers'!I15 -> 0.032451131 | J34: =+'Revenue Build & Growth Drivers'!J15 -> 0.039076893 | K34: =+'Revenue Build & Growth Drivers'!K15 -> 0.043043048
C35: Gross Profit Margin | D35: =+D16/D14 -> 0.27949832 | E35: =+E16/E14 -> 0.29682471 | F35: =+F16/F14 -> 0.30874196 | G35: ='Revenue Build & Growth Drivers'!G46 -> 0.31 | H35: ='Revenue Build & Growth Drivers'!H46 -> 0.315 | I35: ='Revenue Build & Growth Drivers'!I46 -> 0.317 | J35: ='Revenue Build & Growth Drivers'!J46 -> 0.319 | K35: ='Revenue Build & Growth Drivers'!K46 -> 0.321
C36: SG&A % of Revenue | D36: =+D17/D14 -> 0.13828697 | E36: =+E17/E14 -> 0.1374107 | F36: =+F17/F14 -> 0.13644596 | G36: ='Revenue Build & Growth Drivers'!G47 -> 0.135 | H36: ='Revenue Build & Growth Drivers'!H47 -> 0.135 | I36: ='Revenue Build & Growth Drivers'!I47 -> 0.135 | J36: ='Revenue Build & Growth Drivers'!J47 -> 0.135 | K36: ='Revenue Build & Growth Drivers'!K47 -> 0.135
C37: Other Operating Expense % of Revenue | D37: =+D18/D14 -> 0 | E37: =+E18/E14 -> 0 | F37: =+F18/F14 -> 0 | G37: ='Revenue Build & Growth Drivers'!G48 -> 0 | H37: ='Revenue Build & Growth Drivers'!H48 -> 0 | I37: ='Revenue Build & Growth Drivers'!I48 -> 0 | J37: ='Revenue Build & Growth Drivers'!J48 -> 0 | K37: ='Revenue Build & Growth Drivers'!K48 -> 0
C38: EBIT Margin | D38: =+D19/D14 -> 0.14121135 | E38: =+E19/E14 -> 0.15941402 | F38: =+F19/F14 -> 0.172296 | G38: =+G19/G14 -> 0.175 | H38: =+H19/H14 -> 0.18 | I38: =+I19/I14 -> 0.182 | J38: =+J19/J14 -> 0.184 | K38: =+K19/K14 -> 0.186
C39: EBITDA Margin | D39: =+D29/D14 -> 0.16398395 | E39: =+E29/E14 -> 0.18403795 | F39: =+F29/F14 -> 0.19787556 | G39: =+G29/G14 -> 0.19682295 | H39: =+H29/H14 -> 0.2048892 | I39: =+I29/I14 -> 0.20987584 | J39: =+J29/J14 -> 0.21453411 | K39: =+K29/K14 -> 0.2191887
C40: Profit Margin | D40: =+D26/D14 -> 0.092942272 | E40: =+E26/E14 -> 0.11100368 | F40: =+F26/F14 -> 0.11824643 | G40: =+G26/G14 -> 0.12490717 | H40: =+H26/H14 -> 0.13124212 | I40: =+I26/I14 -> 0.13629475 | J40: =+J26/J14 -> 0.14119069 | K40: =+K26/K14 -> 0.14508883
C41: Effective Tax Rate | D41: =+D24/D23 -> 0.25245995 | E41: =+E24/E23 -> 0.25082498 | F41: =+F24/F23 -> 0.25588534 | G41: =+IF(F41<0,AVERAGEIFS(D41:F41,D41:F41,">0"),F41) -> 0.25588534 | H41: =+G41 -> 0.25588534 | I41: =+H41 -> 0.25588534 | J41: =+I41 -> 0.25588534 | K41: =+J41 -> 0.25588534
C43: Balance Sheet | D43: Historical | G43: Projected | M43: 5 Year
D44: =+D$12 -> 44561 | E44: =+E$12 -> 44926 | F44: =+F$12 -> 45291 | G44: =+G$12 -> 45657 | H44: =+H$12 -> 46022 | I44: =+I$12 -> 46387 | J44: =+J$12 -> 46752 | K44: =+K$12 -> 47118 | M44: CAGR
C46: Cash & Short-Term Investments | D46: 139779 | E46: 240069 | F46: 848565 | G46: =+F46+G103 -> 1331866 | H46: =+G46+H103 -> 1868402.9 | I46: =+H46+I103 -> 2067529.4 | J46: =+I46+J103 -> 2757917 | K46: =+J46+K103 -> 3506004.8 | M46: =+_xlfn.RRI(YEAR($K$12)-YEAR($F$12),F46,K46) -> 0.32808379
C47: Short-Term Receivables | D47: 668419 | E47: 836071 | F47: 799009 | G47: =G113 -> 828732.83 | H47: =H113 -> 853050.89 | I47: =I113 -> 880733.35 | J47: =J113 -> 915149.68 | K47: =K113 -> 954540.51
C48: Inventories | D48: 352801 | E48: 438644 | F48: 364731 | G48: =G124 -> 377610.83 | H48: =H124 -> 385874.71 | I48: =I124 -> 397233.58 | J48: =J124 -> 411547.58 | K48: =K124 -> 428001.16
C49: Other Current Assets | D49: 26692 | E49: 34257 | F49: 36939 | G49: =+F49*(1+G34) -> 38313.163 | H49: =+G49*(1+H34) -> 39437.412 | I49: =+H49*(1+I34) -> 40717.2 | J49: =+I49*(1+J34) -> 42308.302 | K49: =+J49*(1+K34) -> 44129.38
C50: Total Current Assets | D50: 1187691 | E50: 1549041 | F50: 2049244 | G50: =+SUM(G46:G49) -> 2576522.8 | H50: =+SUM(H46:H49) -> 3146765.9 | I50: =+SUM(I46:I49) -> 3386213.5 | J50: =+SUM(J46:J49) -> 4126922.6 | K50: =+SUM(K46:K49) -> 4932675.8
C51: Net Property, Plant & Equipment | D51: 421751 | E51: 459376 | F51: 469116 | G51: =+G184+G308+G334 -> 521411.69 | H51: =+H184+H308+H334 -> 562544.26 | I51: =+I184+I308+I334 -> 594613.49 | J51: =+J184+J308+J334 -> 622620.35 | K51: =+K184+K308+K334 -> 642566.81
C52: Total Long-Term Investments | D52: 0 | E52: 0 | F52: 0 | G52: =+F52*(1+G$34) -> 0 | H52: =+G52*(1+H$34) -> 0 | I52: =+H52*(1+I$34) -> 0 | J52: =+I52*(1+J$34) -> 0 | K52: =+J52*(1+K$34) -> 0
C53: Intangible Assets | D53: 2633972 | E53: 2581961 | F53: 2633626 | G53: =+G155+G161 -> 2738628.1 | H53: =+H155+H161 -> 2854942.9 | I53: =+I155+I161 -> 2981080.9 | J53: =+J155+J161 -> 3117561 | K53: =+K155+K161 -> 3264701.7
C54: Deferred Tax Assets | D54: 1905 | E54: 100744 | F54: 103663 | G54: =+F54*(1+G$34) -> 107519.35 | H54: =+G54*(1+H$34) -> 110674.37 | I54: =+H54*(1+I$34) -> 114265.87 | J54: =+I54*(1+J$34) -> 118731.03 | K54: =+J54*(1+K$34) -> 123841.57
C55: Other Assets | D55: 13211 | E55: 16453 | F55: 10865 | G55: =+F55*(1+G$34) -> 11269.188 | H55: =+G55*(1+H$34) -> 11599.867 | I55: =+H55*(1+I$34) -> 11976.295 | J55: =+I55*(1+J$34) -> 12444.292 | K55: =+J55*(1+K$34) -> 12979.932
C56: Total Assets | D56: 4258530 | E56: 4707575 | F56: 5266514 | G56: =+SUM(G50:G55) -> 5955351.1 | H56: =+SUM(H50:H55) -> 6686527.3 | I56: =+SUM(I50:I55) -> 7088150.1 | J56: =+SUM(J50:J55) -> 7998279.2 | K56: =+SUM(K50:K55) -> 8976765.9
C58: ST Debt & Curr. Portion LT Debt | D58: 95618 | E58: 103155 | F58: 114736 | G58: =+G271+G258+G297+G326 -> 118965.39 | H58: =+H271+H258+H297+H326 -> 511025.76 | I58: =+I271+I258+I297+I326 -> 74621.194 | J58: =+J271+J258+J297+J326 -> 77537.159 | K58: =+K271+K258+K297+K326 -> 480874.59
C59: Accounts Payable | D59: 461917 | E59: 487114 | F59: 469585 | G59: =G140 -> 486167.57 | H59: =H140 -> 496807.17 | I59: =I140 -> 511431.53 | J59: =J140 -> 529860.56 | K59: =K140 -> 551044.26
C60: Income Tax Payable | D60: 0 | E60: 0 | F60: 0 | G60: 0 | H60: 0 | I60: 0 | J60: 0 | K60: 0
C61: Other Current Liabilities | D61: 175891 | E61: 199370 | F61: 187217 | G61: =+F61*(1+G34) -> 194181.64 | H61: =+G61*(1+H34) -> 199879.64 | I61: =+H61*(1+I34) -> 206365.96 | J61: =+I61*(1+J34) -> 214430.1 | K61: =+J61*(1+K34) -> 223659.82
C62: Total Current Liabilities | D62: 733426 | E62: 789639 | F62: 771538 | G62: =+SUM(G58:G61) -> 799314.59 | H62: =+SUM(H58:H61) -> 1207712.6 | I62: =+SUM(I58:I61) -> 792418.68 | J62: =+SUM(J58:J61) -> 821827.81 | K62: =+SUM(K58:K61) -> 1255578.7
C64: Long-Term Debt | D64: 1587592 | E64: 1573873 | F64: 1523391 | G64: =+G259+G300+G329 -> 1483129 | H64: =+H259+H300+H329 -> 1051849.8 | I64: =+I259+I300+I329 -> 1059953.7 | J64: =+J259+J300+J329 -> 1069324.8 | K64: =+K259+K300+K329 -> 679631.99
C65: Provision for Risks & Charges | D65: 51875 | E65: 59783 | F65: 58783 | G65: =+F65*(1+G34) -> 60969.779 | H65: =+G65*(1+H34) -> 62758.855 | I65: =+H65*(1+I34) -> 64795.451 | J65: =+I65*(1+J34) -> 67327.456 | K65: =+J65*(1+K34) -> 70225.435
C66: Deferred Tax Liabilities | D66: 248243 | E66: 352225 | F66: 347593 | G66: =+F66*(1+G34) -> 360523.76 | H66: =+G66*(1+H34) -> 371102.85 | I66: =+H66*(1+I34) -> 383145.56 | J66: =+I66*(1+J34) -> 398117.7 | K66: =+J66*(1+K34) -> 415253.89
C67: Other Liabilities | D67: 960 | E67: 2349 | F67: 1554 | G67: =+F67*(1+G34) -> 1611.8102 | H67: =+G67*(1+H34) -> 1659.1066 | I67: =+H67*(1+I34) -> 1712.9465 | J67: =+I67*(1+J34) -> 1779.8831 | K67: =+J67*(1+K34) -> 1856.4947
C68: Total Liabilities | D68: 2622096 | E68: 2777869 | F68: 2702859 | G68: =+SUM(G64:G67,G62) -> 2705549 | H68: =+SUM(H64:H67,H62) -> 2695083.2 | I68: =+SUM(I64:I67,I62) -> 2302026.3 | J68: =+SUM(J64:J67,J62) -> 2358377.6 | K68: =+SUM(K64:K67,K62) -> 2422546.5
C70: Total Shareholder's Equity | D70: 1636434 | E70: 1929706 | F70: 2563655 | G70: =+F70+G31+G214-G215+G95 -> 3249802.2 | H70: =+G70+H31+H214-H215+H95 -> 3991444.1 | I70: =+H70+I31+I214-I215+I95 -> 4786123.8 | J70: =+I70+J31+J214-J215+J95 -> 5639901.6 | K70: =+J70+K31+K214-K215+K95 -> 6554219.4
C71: Total Equity | D71: 1636434 | E71: 1929706 | F71: 2563655 | G71: =+G70+G227 -> 3249802.2 | H71: =+H70+H227 -> 3991444.1 | I71: =+I70+I227 -> 4786123.8 | J71: =+J70+J227 -> 5639901.6 | K71: =+K70+K227 -> 6554219.4
C73: Total Liabilities and Equity | D73: 4258530 | E73: 4707575 | F73: 5266514 | G73: =+G71+G68 -> 5955351.1 | H73: =+H71+H68 -> 6686527.3 | I73: =+I71+I68 -> 7088150.1 | J73: =+J71+J68 -> 7998279.2 | K73: =+K71+K68 -> 8976765.9
C75: Balance Check | D75: =+D56-D73 -> 0 | E75: =+E56-E73 -> 0 | F75: =+F56-F73 -> 0 | G75: =+G56-G73 -> 0 | H75: =+H56-H73 -> 0 | I75: =+I56-I73 -> 0 | J75: =+J56-J73 -> 0 | K75: =+K56-K73 -> 0
C77: Cash Flow Statement | D77: Historical | G77: Projected
D78: =+D$12 -> 44561 | E78: =+E$12 -> 44926 | F78: =+F$12 -> 45291 | G78: =+G$12 -> 45657 | H78: =+H$12 -> 46022 | I78: =+I$12 -> 46387 | J78: =+J$12 -> 46752 | K78: =+K$12 -> 47118
C80: Net Income | D80: 324016 | E80: 555989 | F80: 614254 | G80: =+G26+G25 -> 672992.49 | H80: =+H26+H25 -> 727874.43 | I80: =+I26+I25 -> 780426.23 | J80: =+J26+J25 -> 840052.63 | K80: =+K26+K25 -> 900402.37
C81: Depreciation, Depletion & Amortization | D81: 79390 | E81: 123335 | F81: 132878 | G81: =+G28 -> 117580.75 | H81: =+H28 -> 138036.58 | I81: =+I28 -> 159617.58 | J81: =+J28 -> 181671.05 | K81: =+K28 -> 205964.72
C82: Deferred Taxes & Investment Tax Credit | D82: -2818 | E82: 6041 | F82: -7476 | G82: =+F54-G54+G66-F66 -> 9074.4096 | H82: =+G54-H54+H66-G66 -> 7424.0751 | I82: =+H54-I54+I66-H66 -> 8451.1988 | J82: =+I54-J54+J66-I66 -> 10506.983 | K82: =+J54-K54+K66-J66 -> 12025.654
C83: Other Funds | D83: 38741 | E83: 29179 | F83: 32343 | G83: =+G31+F55-G55+G65-F65+G67-F67+F261-G261+G311-G314 -> 59250.965 | H83: =+H31+G55-H55+H65-G65+H67-G67+G261-H261+H311-H314 -> 60742.843 | I83: =+I31+H55-I55+I65-H65+I67-H67+H261-I261+I311-I314 -> 62818.622 | J83: =+J31+I55-J55+J65-I65+J67-I67+I261-J261+J311-J314 -> 64425.058 | K83: =+K31+J55-K55+K65-J65+K67-J67+J261-K261+K311-K314 -> 66889.214
C84: Funds from Operations | D84: 439329 | E84: 714544 | F84: 771999 | G84: =+SUM(G80:G83) -> 858898.62 | H84: =+SUM(H80:H83) -> 934077.93 | I84: =+SUM(I80:I83) -> 1011313.6 | J84: =+SUM(J80:J83) -> 1096655.7 | K84: =+SUM(K80:K83) -> 1185282
C85: Changes in Working Capital | D85: -36304 | E85: -218743 | F85: 77410 | G85: =+F47-G47+F48-G48+F49-G49+G59-F59+G60-F60+G61-F61 -> -20430.627 | H85: =+G47-H47+G48-H48+G49-H49+H59-G59+H60-G60+H61-G61 -> -17368.576 | I85: =+H47-I47+H48-I48+H49-I49+I59-H59+I60-H60+I61-H61 -> -19210.451 | J85: =+I47-J47+I48-J48+I49-J49+J59-I59+J60-I60+J61-I61 -> -23828.252 | K85: =+J47-K47+J48-K48+J49-K49+K59-J59+K60-J60+K61-J61 -> -27252.058
C86: Cash Flow From Operating Activities | D86: 403025 | E86: 495801 | F86: 849409 | G86: =+SUM(G84:G85) -> 838467.99 | H86: =+SUM(H84:H85) -> 916709.35 | I86: =+SUM(I84:I85) -> 992103.17 | J86: =+SUM(J84:J85) -> 1072827.5 | K86: =+SUM(K84:K85) -> 1158029.9
C88: Capital Expenditures | D88: -55546 | E88: -76382 | F88: -63998 | G88: =-G181 -> -78129.97 | H88: =-H181 -> -77774.945 | I88: =-I181 -> -77958.359 | J88: =-J181 -> -83572.81 | K88: =-K181 -> -86229.828
C89: Net Assets from Acquisitions | D89: -1267114 | E89: -20500 | F89: -149154 | G89: =-G341 -> -228101.41 | H89: =-H341 -> -251680.32 | I89: =-I341 -> -274243.44 | J89: =-J341 -> -296776.4 | K89: =-K341 -> -321540.02
C90: Sale of Fixed Assets & Businesses | D90: 415 | E90: 2975 | F90: 14982 | G90: 0 | H90: 0 | I90: 0 | J90: 0 | K90: 0
C91: Purchase/Sale of Investments | D91: 0 | E91: 0 | F91: 0 | G91: =+F52-G52 -> 0 | H91: =+G52-H52 -> 0 | I91: =+H52-I52 -> 0 | J91: =+I52-J52 -> 0 | K91: =+J52-K52 -> 0
C92: Other Funds | D92: 0 | E92: 0 | F92: 0 | G92: 0 | H92: 0 | I92: 0 | J92: 0 | K92: 0
C93: Cash Flow From Investing Activities | D93: -1322245 | E93: -93907 | F93: -198170 | G93: =+SUM(G88:G92) -> -306231.38 | H93: =+SUM(H88:H92) -> -329455.27 | I93: =+SUM(I88:I92) -> -352201.8 | J93: =+SUM(J88:J92) -> -380349.21 | K93: =+SUM(K88:K92) -> -407769.85
C95: Change in Capital Stock | D95: -32253 | E95: -248022 | F95: 3130 | G95: 0 | H95: 0 | I95: 0 | J95: 0 | K95: 0
C96: Issuance/Reduction of Debt, Net | D96: 770715 | E96: -38658 | F96: -40138 | G96: =+G270-F258 -> -47039 | H96: =+H270-G258 -> -48750 | I96: =+I270-H258 -> -438750 | J96: =+J270-I258 -> 0 | K96: =+K270-J258 -> 0
C97: Dividends | D97: 0 | E97: 0 | F97: 0 | G97: =-G215 -> 0 | H97: =-H215 -> 0 | I97: =-I215 -> 0 | J97: =-J215 -> 0 | K97: =-K215 -> 0
C98: Other Funds | D98: -9455 | E98: -13393 | F98: -6828 | G98: =-G293 -> -1896.6207 | H98: =-H293 -> -1967.1767 | I98: =-I293 -> -2024.9008 | J98: =-J293 -> -2090.6112 | K98: =-K293 -> -2172.3057
C99: Cash Flow From Financing Activities | D99: 729007 | E99: -300073 | F99: -43836 | G99: =+SUM(G95:G98) -> -48935.621 | H99: =+SUM(H95:H98) -> -50717.177 | I99: =+SUM(I95:I98) -> -440774.9 | J99: =+SUM(J95:J98) -> -2090.6112 | K99: =+SUM(K95:K98) -> -2172.3057
C101: Effect of Exchange Rate on Cash and Equivalents | D101: -15 | E101: -1531 | F101: 1093 | G101: 0 | H101: 0 | I101: 0 | J101: 0 | K101: 0
C103: Net Change in Cash During Period | D103: -190228 | E103: 100290 | F103: 608496 | G103: =+G86+G93+G99+G101 -> 483300.99 | H103: =+H86+H93+H99+H101 -> 536536.91 | I103: =+I86+I93+I99+I101 -> 199126.47 | J103: =+J86+J93+J99+J101 -> 690387.65 | K103: =+K86+K93+K99+K101 -> 748087.74
C105: Line Item Schedules
C107: Current Assets Schedule | D107: Historical | G107: Projected
D108: =+D$12 -> 44561 | E108: =+E$12 -> 44926 | F108: =+F$12 -> 45291 | G108: =+G$12 -> 45657 | H108: =+H$12 -> 46022 | I108: =+I$12 -> 46387 | J108: =+J$12 -> 46752 | K108: =+K$12 -> 47118
C110: Accounts Receivable
C111: Beginning of Period | E111: =+D113 -> 668419 | F111: =+E113 -> 836071 | G111: =+F113 -> 799009 | H111: =+G113 -> 828732.83 | I111: =+H113 -> 853050.89 | J111: =+I113 -> 880733.35 | K111: =+J113 -> 915149.68
C112: Increase (Decrease) | E112: =+E113-E111 -> 167652 | F112: =+F113-F111 -> -37062 | G112: =+G113-G111 -> 29723.835 | H112: =+H113-H111 -> 24318.054 | I112: =+I113-I111 -> 27682.466 | J112: =+J113-J111 -> 34416.323 | K112: =+K113-K111 -> 39390.831
C113: End of Period | D113: =+D47 -> 668419 | E113: =+E47 -> 836071 | F113: =+F47 -> 799009 | G113: =+IF($E$115=1,F113*(1+G117),IF($E$115=2,G119*G118/365,"NA")) -> 828732.83 | H113: =+IF($E$115=1,G113*(1+H117),IF($E$115=2,H119*H118/365,"NA")) -> 853050.89 | I113: =+IF($E$115=1,H113*(1+I117),IF($E$115=2,I119*I118/365,"NA")) -> 880733.35 | J113: =+IF($E$115=1,I113*(1+J117),IF($E$115=2,J119*J118/365,"NA")) -> 915149.68 | K113: =+IF($E$115=1,J113*(1+K117),IF($E$115=2,K119*K118/365,"NA")) -> 954540.51
C115: A/R Forecasting Approach (1=Rev Growth, 2=DSO) | E115: 1
C117: Revenue Growth Rate (Approach 1) | E117: =+E34 -> 0.43673167 | F117: =+F34 -> 0.037125076 | G117: =+G34 -> 0.037200876 | H117: =+H34 -> 0.029343659 | I117: =+I34 -> 0.032451131 | J117: =+J34 -> 0.039076893 | K117: =+K34 -> 0.043043048
C118: Days Sales Outstanding (Approach 2) | D118: =+D113*365/D119 -> 69.982343 | E118: =+E113*365/E119 -> 60.926635 | F118: =+F113*365/F119 -> 56.141572 | G118: =+'Revenue Build & Growth Drivers'!G49 -> 55 | H118: =+'Revenue Build & Growth Drivers'!H49 -> 55 | I118: =+'Revenue Build & Growth Drivers'!I49 -> 55 | J118: =+'Revenue Build & Growth Drivers'!J49 -> 55 | K118: =+'Revenue Build & Growth Drivers'!K49 -> 55
C119: Revenue | D119: =+D14 -> 3486207 | E119: =+E14 -> 5008744 | F119: =+F14 -> 5194694 | G119: =+G14 -> 5387941.2 | H119: =+H14 -> 5546043.1 | I119: =+I14 -> 5726018.4 | J119: =+J14 -> 5949773.4 | K119: =+K14 -> 6205869.8
C121: Inventories
C122: Beginning of Period | E122: =+D124 -> 352801 | F122: =+E124 -> 438644 | G122: =+F124 -> 364731 | H122: =+G124 -> 377610.83 | I122: =+H124 -> 385874.71 | J122: =+I124 -> 397233.58 | K122: =+J124 -> 411547.58
C123: Increase (Decrease) | E123: =+E124-E122 -> 85843 | F123: =+F124-F122 -> -73913 | G123: =+G124-G122 -> 12879.834 | H123: =+H124-H122 -> 8263.8797 | I123: =+I124-I122 -> 11358.868 | J123: =+J124-J122 -> 14313.997 | K123: =+K124-K122 -> 16453.581
C124: End of Period | D124: =+D48 -> 352801 | E124: =+E48 -> 438644 | F124: =+F48 -> 364731 | G124: =+IF($E$126=1,F124*(1+G128),IF($E$126=2,G130/G129,"NA")) -> 377610.83 | H124: =+IF($E$126=1,G124*(1+H128),IF($E$126=2,H130/H129,"NA")) -> 385874.71 | I124: =+IF($E$126=1,H124*(1+I128),IF($E$126=2,I130/I129,"NA")) -> 397233.58 | J124: =+IF($E$126=1,I124*(1+J128),IF($E$126=2,J130/J129,"NA")) -> 411547.58 | K124: =+IF($E$126=1,J124*(1+K128),IF($E$126=2,K130/K129,"NA")) -> 428001.16
C126: Inventory Forecasting Approach (1=Cost of Sales Growth, 2=Turnover) | E126: 1
C128: Cost of Sales Growth Rate (Approach 1) | E128: =+E130/D130-1 -> 0.40218161 | F128: =+F130/E130-1 -> 0.019548129 | G128: =+G130/F130-1 -> 0.035313243 | H128: =+H130/G130-1 -> 0.021884647 | I128: =+I130/H130-1 -> 0.029436675 | J128: =+J130/I130-1 -> 0.036034208 | K128: =+K130/J130-1 -> 0.039979779
...

Sheet Integrated DCF Model
C2: ="Discounted Cash Flow Model For "&D5 -> Discounted Cash Flow Model For TopBuild Corp.
C3: $ in thousands except per share | J3: Values
C5: Company Name | D5: ='Revenue Build & Growth Drivers'!D5 -> TopBuild Corp. | G5: Basic Shares Outstanding | J5: =+D66 -> 31775.877
C6: Ticker | D6: ='Revenue Build & Growth Drivers'!D6 -> BLD | G6: Fully Diluted Shares Outstanding | J6: =+D71 -> 32100.077
C7: Valuation Date | D7: ='Revenue Build & Growth Drivers'!D7 -> 45394 | G7: Discount Rate (WACC) | J7: =+'WACC Build'!D43 -> 0.11325886
C8: Latest Adj. Closing Share Price Date | D8: ='Revenue Build & Growth Drivers'!D8 -> 45393 | G8: Midyear Adjustment (1=on, 0=off) | J8: 0
C9: Latest Adj. Closing Share Price | D9: ='Revenue Build & Growth Drivers'!D9 -> 421.45
C11: Unlevered Free Cash Flow | E11: Historical | H11: Projected | N11: 5 Year
E12: ='Financial Statement Model'!D12 -> 44561 | F12: ='Financial Statement Model'!E12 -> 44926 | G12: ='Financial Statement Model'!F12 -> 45291 | H12: ='Financial Statement Model'!G12 -> 45657 | I12: ='Financial Statement Model'!H12 -> 46022 | J12: ='Financial Statement Model'!I12 -> 46387 | K12: ='Financial Statement Model'!J12 -> 46752 | L12: ='Financial Statement Model'!K12 -> 47118 | N12: CAGR
C14: Total Revenues | E14: =+'Financial Statement Model'!D14 -> 3486207 | F14: =+'Financial Statement Model'!E14 -> 5008744 | G14: =+'Financial Statement Model'!F14 -> 5194694 | H14: =+'Financial Statement Model'!G14 -> 5387941.2 | I14: =+'Financial Statement Model'!H14 -> 5546043.1 | J14: =+'Financial Statement Model'!I14 -> 5726018.4 | K14: =+'Financial Statement Model'!J14 -> 5949773.4 | L14: =+'Financial Statement Model'!K14 -> 6205869.8
C15: YoY Growth Rate (%) | F15: =+F14/E14-1 -> 0.43673167 | G15: =+G14/F14-1 -> 0.037125076 | H15: =+H14/G14-1 -> 0.037200876 | I15: =+I14/H14-1 -> 0.029343659 | J15: =+J14/I14-1 -> 0.032451131 | K15: =+K14/J14-1 -> 0.039076893 | L15: =+L14/K14-1 -> 0.043043048
C17: Gross Profit | E17: =+'Financial Statement Model'!D16 -> 974389 | F17: =+'Financial Statement Model'!E16 -> 1486719 | G17: =+'Financial Statement Model'!F16 -> 1603820 | H17: =+'Financial Statement Model'!G16 -> 1670261.8 | I17: =+'Financial Statement Model'!H16 -> 1747003.6 | J17: =+'Financial Statement Model'!I16 -> 1815147.8 | K17: =+'Financial Statement Model'!J16 -> 1897977.7 | L17: =+'Financial Statement Model'!K16 -> 1992084.2
C18: Gross Margin (%) | E18: =+E17/E$14 -> 0.27949832 | F18: =+F17/F$14 -> 0.29682471 | G18: =+G17/G$14 -> 0.30874196 | H18: =+H17/H$14 -> 0.31 | I18: =+I17/I$14 -> 0.315 | J18: =+J17/J$14 -> 0.317 | K18: =+K17/K$14 -> 0.319 | L18: =+L17/L$14 -> 0.321
C20: EBITDA | E20: =+'Financial Statement Model'!D29 -> 571682 | F20: =+'Financial Statement Model'!E29 -> 921799 | G20: =+'Financial Statement Model'!F29 -> 1027903 | H20: =+'Financial Statement Model'!G29 -> 1060470.5 | I20: =+'Financial Statement Model'!H29 -> 1136324.3 | J20: =+'Financial Statement Model'!I29 -> 1201752.9 | K20: =+'Financial Statement Model'!J29 -> 1276429.4 | L20: =+'Financial Statement Model'!K29 -> 1360256.5 | N20: =+_xlfn.RRI(YEAR($L$12)-YEAR($G$12),G20,L20) -> 0.057629939
C21: EBITDA Margin (%) | E21: =+E20/E$14 -> 0.16398395 | F21: =+F20/F$14 -> 0.18403795 | G21: =+G20/G$14 -> 0.19787556 | H21: =+H20/H$14 -> 0.19682295 | I21: =+I20/I$14 -> 0.2048892 | J21: =+J20/J$14 -> 0.20987584 | K21: =+K20/K$14 -> 0.21453411 | L21: =+L20/L$14 -> 0.2191887
C23: Operating Profit (EBIT) | E23: =+'Financial Statement Model'!D19 -> 492292 | F23: =+'Financial Statement Model'!E19 -> 798464 | G23: =+'Financial Statement Model'!F19 -> 895025 | H23: =+'Financial Statement Model'!G19 -> 942889.7 | I23: =+'Financial Statement Model'!H19 -> 998287.75 | J23: =+'Financial Statement Model'!I19 -> 1042135.4 | K23: =+'Financial Statement Model'!J19 -> 1094758.3 | L23: =+'Financial Statement Model'!K19 -> 1154291.8
C24: EBIT Margin (%) | E24: =+E23/E$14 -> 0.14121135 | F24: =+F23/F$14 -> 0.15941402 | G24: =+G23/G$14 -> 0.172296 | H24: =+H23/H$14 -> 0.175 | I24: =+I23/I$14 -> 0.18 | J24: =+J23/J$14 -> 0.182 | K24: =+K23/K$14 -> 0.184 | L24: =+L23/L$14 -> 0.186
C26: Tax on EBIT | E26: =+E23*E27 -> 124284.02 | F26: =+F23*F27 -> 200274.72 | G26: =+G23*G27 -> 229023.78 | H26: =+H23*H27 -> 241271.65 | I26: =+I23*I27 -> 255447.2 | J26: =+J23*J27 -> 266667.16 | K26: =+K23*K27 -> 280132.61 | L26: =+L23*L27 -> 295366.35
C27: Tax Rate (%) | E27: =+'Financial Statement Model'!D41 -> 0.25245995 | F27: =+'Financial Statement Model'!E41 -> 0.25082498 | G27: =+'Financial Statement Model'!F41 -> 0.25588534 | H27: =+'Financial Statement Model'!G41 -> 0.25588534 | I27: =+'Financial Statement Model'!H41 -> 0.25588534 | J27: =+'Financial Statement Model'!I41 -> 0.25588534 | K27: =+'Financial Statement Model'!J41 -> 0.25588534 | L27: =+'Financial Statement Model'!K41 -> 0.25588534
C29: NOPAT/EBIAT | E29: =+E23-E26 -> 368007.98 | F29: =+F23-F26 -> 598189.28 | G29: =+G23-G26 -> 666001.22 | H29: =+H23-H26 -> 701618.05 | I29: =+I23-I26 -> 742840.55 | J29: =+J23-J26 -> 775468.19 | K29: =+K23-K26 -> 814625.71 | L29: =+L23-L26 -> 858925.44
C31: Plus: Depreciation and Amortization | F31: =+'Financial Statement Model'!E28 -> 123335 | G31: =+'Financial Statement Model'!F28 -> 132878 | H31: =+'Financial Statement Model'!G28 -> 117580.75 | I31: =+'Financial Statement Model'!H28 -> 138036.58 | J31: =+'Financial Statement Model'!I28 -> 159617.58 | K31: =+'Financial Statement Model'!J28 -> 181671.05 | L31: =+'Financial Statement Model'!K28 -> 205964.72
C32: Plus: Stock Compensation | F32: =+'Financial Statement Model'!E31 -> 12310 | G32: =+'Financial Statement Model'!F31 -> 15838 | H32: =+'Financial Statement Model'!G31 -> 13154.667 | I32: =+'Financial Statement Model'!H31 -> 13767.556 | J32: =+'Financial Statement Model'!I31 -> 14253.407 | K32: =+'Financial Statement Model'!J31 -> 13725.21 | L32: =+'Financial Statement Model'!K31 -> 13915.391
C33: Less: Change in Net Working Capital | F33: =F52 -> 212384 | G33: =G52 -> -78611 | H33: =H52 -> 20430.627 | I33: =I52 -> 17368.576 | J33: =J52 -> 19210.451 | K33: =K52 -> 23828.252 | L33: =L52 -> 27252.058
C34: Less: Capital Expenditures & Acquisition Spend | F34: =+'Financial Statement Model'!E181-'Financial Statement Model'!E89 -> 96882 | G34: =+'Financial Statement Model'!F181-'Financial Statement Model'!F89 -> 213152 | H34: =+'Financial Statement Model'!G181-'Financial Statement Model'!G89 -> 306231.38 | I34: =+'Financial Statement Model'!H181-'Financial Statement Model'!H89 -> 329455.27 | J34: =+'Financial Statement Model'!I181-'Financial Statement Model'!I89 -> 352201.8 | K34: =+'Financial Statement Model'!J181-'Financial Statement Model'!J89 -> 380349.21 | L34: =+'Financial Statement Model'!K181-'Financial Statement Model'!K89 -> 407769.85
C36: Unlevered Free Cash Flow (UFCF) | F36: =+F29+F31+F32-F33-F34 -> 424568.28 | G36: =+G29+G31+G32-G33-G34 -> 680176.22 | H36: =+H29+H31+H32-H33-H34 -> 505691.47 | I36: =+I29+I31+I32-I33-I34 -> 547820.84 | J36: =+J29+J31+J32-J33-J34 -> 577926.92 | K36: =+K29+K31+K32-K33-K34 -> 605844.51 | L36: =+L29+L31+L32-L33-L34 -> 643783.65 | N36: =+_xlfn.RRI(YEAR($L$12)-YEAR($G$12),G36,L36) -> -0.010937584
C38: Net Working Capital Schedule | E38: Historical | H38: Projected
E39: ='Financial Statement Model'!D12 -> 44561 | F39: ='Financial Statement Model'!E12 -> 44926 | G39: ='Financial Statement Model'!F12 -> 45291 | H39: ='Financial Statement Model'!G12 -> 45657 | I39: ='Financial Statement Model'!H12 -> 46022 | J39: ='Financial Statement Model'!I12 -> 46387 | K39: ='Financial Statement Model'!J12 -> 46752 | L39: ='Financial Statement Model'!K12 -> 47118
C41: Short-Term Receivables | E41: =+'Financial Statement Model'!D47 -> 668419 | F41: =+'Financial Statement Model'!E47 -> 836071 | G41: =+'Financial Statement Model'!F47 -> 799009 | H41: =+'Financial Statement Model'!G47 -> 828732.83 | I41: =+'Financial Statement Model'!H47 -> 853050.89 | J41: =+'Financial Statement Model'!I47 -> 880733.35 | K41: =+'Financial Statement Model'!J47 -> 915149.68 | L41: =+'Financial Statement Model'!K47 -> 954540.51
C42: Inventories | E42: =+'Financial Statement Model'!D48 -> 352801 | F42: =+'Financial Statement Model'!E48 -> 438644 | G42: =+'Financial Statement Model'!F48 -> 364731 | H42: =+'Financial Statement Model'!G48 -> 377610.83 | I42: =+'Financial Statement Model'!H48 -> 385874.71 | J42: =+'Financial Statement Model'!I48 -> 397233.58 | K42: =+'Financial Statement Model'!J48 -> 411547.58 | L42: =+'Financial Statement Model'!K48 -> 428001.16
C43: Other Current Assets | E43: =+'Financial Statement Model'!D49 -> 26692 | F43: =+'Financial Statement Model'!E49 -> 34257 | G43: =+'Financial Statement Model'!F49 -> 36939 | H43: =+'Financial Statement Model'!G49 -> 38313.163 | I43: =+'Financial Statement Model'!H49 -> 39437.412 | J43: =+'Financial Statement Model'!I49 -> 40717.2 | K43: =+'Financial Statement Model'!J49 -> 42308.302 | L43: =+'Financial Statement Model'!K49 -> 44129.38
C44: Current Assets (Ex. Cash) | E44: =SUM(E41:E43) -> 1047912 | F44: =SUM(F41:F43) -> 1308972 | G44: =SUM(G41:G43) -> 1200679 | H44: =SUM(H41:H43) -> 1244656.8 | I44: =SUM(I41:I43) -> 1278363 | J44: =SUM(J41:J43) -> 1318684.1 | K44: =SUM(K41:K43) -> 1369005.6 | L44: =SUM(L41:L43) -> 1426671
C46: Accounts Payable | E46: =+'Financial Statement Model'!D59 -> 461917 | F46: =+'Financial Statement Model'!E59 -> 487114 | G46: =+'Financial Statement Model'!F59 -> 469585 | H46: =+'Financial Statement Model'!G59 -> 486167.57 | I46: =+'Financial Statement Model'!H59 -> 496807.17 | J46: =+'Financial Statement Model'!I59 -> 511431.53 | K46: =+'Financial Statement Model'!J59 -> 529860.56 | L46: =+'Financial Statement Model'!K59 -> 551044.26
C47: Other Current Liabilities | E47: =+'Financial Statement Model'!D61 -> 175891 | F47: =+'Financial Statement Model'!E61 -> 199370 | G47: =+'Financial Statement Model'!F61 -> 187217 | H47: =+'Financial Statement Model'!G61 -> 194181.64 | I47: =+'Financial Statement Model'!H61 -> 199879.64 | J47: =+'Financial Statement Model'!I61 -> 206365.96 | K47: =+'Financial Statement Model'!J61 -> 214430.1 | L47: =+'Financial Statement Model'!K61 -> 223659.82
C48: Current Liabilities | E48: =SUM(E46:E47) -> 637808 | F48: =SUM(F46:F47) -> 686484 | G48: =SUM(G46:G47) -> 656802 | H48: =SUM(H46:H47) -> 680349.21 | I48: =SUM(I46:I47) -> 696686.81 | J48: =SUM(J46:J47) -> 717797.48 | K48: =SUM(K46:K47) -> 744290.65 | L48: =SUM(L46:L47) -> 774704.08
C50: Net Working Capital | E50: =+E44-E48 -> 410104 | F50: =+F44-F48 -> 622488 | G50: =+G44-G48 -> 543877 | H50: =+H44-H48 -> 564307.63 | I50: =+I44-I48 -> 581676.2 | J50: =+J44-J48 -> 600886.65 | K50: =+K44-K48 -> 624714.91 | L50: =+L44-L48 -> 651966.96
C52: Change in Net Working Capital | F52: =+F50-E50 -> 212384 | G52: =+G50-F50 -> -78611 | H52: =+H50-G50 -> 20430.627 | I52: =+I50-H50 -> 17368.576 | J52: =+J50-I50 -> 19210.451 | K52: =+K50-J50 -> 23828.252 | L52: =+L50-K50 -> 27252.058
C54: ="Present Value of UFCFs as of "&TEXT(D7,("mmm dd, yyyy")) -> Present Value of UFCFs as of Apr 12, 2024 | F54: Stub % | H54: Stub Year | I54: Year 2 | J54: Year 3 | K54: Year 4 | L54: Year 5
C55: Dates for Discounting UFCF | F55: =YEARFRAC(D7,H55,1) -> 0.71857923 | H55: =IF($J$8=0,H$12,AVERAGE(D7,H12)) -> 45657 | I55: =IF($J$8=0,I$12,AVERAGE(H12:I12)) -> 46022 | J55: =IF($J$8=0,J$12,AVERAGE(I12:J12)) -> 46387 | K55: =IF($J$8=0,K$12,AVERAGE(J12:K12)) -> 46752 | L55: =IF($J$8=0,L$12,AVERAGE(K12:L12)) -> 47118
C57: Periods for Discounting UFCF | H57: =+YEARFRAC($D$7,H55,1) -> 0.71857923 | I57: =+YEARFRAC($D$7,I55,1) -> 1.7181943 | J57: =+YEARFRAC($D$7,J55,1) -> 2.7180657 | K57: =+YEARFRAC($D$7,K55,1) -> 3.7180014 | L57: =+YEARFRAC($D$7,L55,1) -> 4.7181171
C59: Stub-adjusted Unlevered Free Cash Flow (UFCF) | H59: =+H36*F55 -> 363379.39 | I59: =+I36 -> 547820.84 | J59: =+J36 -> 577926.92 | K59: =+K36 -> 605844.51 | L59: =+L36 -> 643783.65
C61: PV of Stub-adjusted UFCFs | H61: =+H59/(1+$J$7)^H57 -> 336416.47 | I61: =+I59/(1+$J$7)^I57 -> 455593.27 | J61: =+J59/(1+$J$7)^J57 -> 431739.22 | K61: =+K59/(1+$J$7)^K57 -> 406552.46 | L61: =+L59/(1+$J$7)^L57 -> 388055.46
C63: Basic to Fully Diluted Shares Bridge (in 000s)
C66: Basic Shares | D66: 31775.877
C67: Restricted Stock | D67: 195.5
C68: Options/Warrants | D68: 128.7
C69: Convertible Debt | D69: 0
C70: Convertible Preferred Stock | D70: 0
C71: Fully Diluted Shares Outstanding | D71: =SUM(D66:D70) -> 32100.077
C73: Terminal Value and Equity Value Bridge
C76: Terminal Value - Multiples Method | H76: Terminal Value - Perpetual Growth Method
C78: EV/EBITDA | E78: 10 | H78: Terminal UFCF Growth Rate | L78: 0.06
C80: Implied Terminal Value | E80: =+E78*L20 -> 13602565 | H80: Implied Terminal Value | L80: =+L59*(1+L78)/(J7-L78) -> 12813092
C81: Implied Terminal UFCF Growth Rate | E81: =+(E80*J7-L59)/(E80+L59) -> 0.062951383 | H81: Implied Terminal EV/EBITDA | L81: =+L80/L20 -> 9.4196147
C83: Plus: PV of Terminal Value | E83: =+E80/(1+J7)^L57 -> 8199260.3 | H83: Plus: PV of Terminal Value | L83: =+L80/(1+J7)^L57 -> 7723387.3
C84: Plus: Sum of PV of Stub-adjusted UFCFs | E84: =+SUM(H61:L61) -> 2018356.9 | H84: Plus: Sum of PV of Stub-adjusted UFCFs | L84: =+SUM(H61:L61) -> 2018356.9
C85: Implied Enterprise Value | E85: =+E83+E84 -> 10217617 | H85: Implied Enterprise Value | L85: =SUM(L83:L84) -> 9741744.1
C87: % of Implied EV from Terminal Value | E87: =+E83/E85 -> 0.80246306 | H87: % of Implied EV from Terminal Value | L87: =+L83/L85 -> 0.7928136
C89: Plus: Cash and Cash Equivalents | E89: =+'Financial Statement Model'!F46 -> 848565 | H89: Plus: Cash and Cash Equivalents | L89: =+E89 -> 848565
C90: Less: Debt & Capital Leases (excl. Operating Leases) | E90: =+'Financial Statement Model'!F258+'Financial Statement Model'!F259+'Financial Statement Model'!F271+'Financial Statement Model'!F297+'Financial Statement Model'!F300 -> 1426134 | H90: Less: Debt & Capital Leases (excl. Operating Leases) | L90: =+E90 -> 1426134
C91: Less: Preferred Stock | E91: 0 | H91: Less: Preferred Stock | L91: =+E91 -> 0
C92: Less: Non-controlling Interest | E92: =+'Financial Statement Model'!F227 -> 0 | H92: Less: Non-controlling Interest | L92: =+E92 -> 0
C93: Implied Equity Value | E93: =+E85+E89-E90-E91-E92 -> 9640048.2 | H93: Implied Equity Value | L93: =+L85+L89-L90-L91-L92 -> 9164175.1
C95: Implied Share Price | E95: =+E93/D71 -> 300.31231 | H95: Implied Share Price | L95: =+L93/D71 -> 285.48764
C96: Premium (Discount) to Current Price | E96: =+E95/D9-1 -> -0.28743076 | H96: Premium (Discount) to Current Price | L96: =+L95/D9-1 -> -0.32260615
C98: Implied Y1 Multiples | H98: Implied Y1 Multiples
C99: EV / Revenue | E99: =+E$85/$H14 -> 1.8963862 | H99: EV / Revenue | L99: =+L$85/$H14 -> 1.8080643
C100: EV / EBITDA | E100: =+E$85/$H20 -> 9.6349852 | H100: EV / EBITDA | L100: =+L$85/$H20 -> 9.1862475
C101: EV / EBIT | E101: =+E$85/$H23 -> 10.836492 | H101: EV / EBIT | L101: =+L$85/$H23 -> 10.331796
C103: Data Tables and Football Field
E106: EV/EBITDA Multiple
D107: Discount Rate (WACC) | E107: =E95 -> 300.31231 | F107: =+G107-0.5 -> 8.5 | G107: =+H107-0.5 -> 9 | H107: =+I107-0.5 -> 9.5 | I107: 10 | J107: =+I107+0.5 -> 10.5 | K107: =+J107+0.5 -> 11 | L107: =+K107+0.5 -> 11.5
E108: =+E109-0.5% -> 0.098258859 | F108: 278.74531 | G108: 292.36086 | H108: 305.97641 | I108: 319.59196 | J108: 333.20751 | K108: 346.82305 | L108: 360.4386
E109: =+E110-0.5% -> 0.10325886 | F109: 273.02253 | G109: 286.34938 | H109: 299.67624 | I109: 313.00309 | J109: 326.32994 | K109: 339.6568 | L109: 352.98365
E110: =+E111-0.5% -> 0.10825886 | F110: 267.44151 | G110: 280.48706 | H110: 293.53261 | I110: 306.57815 | J110: 319.6237 | K110: 332.66925 | L110: 345.71479
E111: 0.11325886 | F111: 261.9981 | G111: 274.7695 | H111: 287.5409 | I111: 300.31231 | J111: 313.08371 | K111: 325.85511 | L111: 338.62652
E112: =+E111+0.5% -> 0.11825886 | F112: 256.68825 | G112: 269.19246 | H112: 281.69667 | I112: 294.20088 | J112: 306.70509 | K112: 319.2093 | L112: 331.71351
E113: =+E112+0.5% -> 0.12325886 | F113: 251.50808 | G113: 263.75184 | H113: 275.9956 | I113: 288.23937 | J113: 300.48313 | K113: 312.72689 | L113: 324.97065
E114: =+E113+0.5% -> 0.12825886 | F114: 246.45381 | G114: 258.44367 | H114: 270.43353 | I114: 282.42339 | J114: 294.41325 | K114: 306.40311 | L114: 318.39297
E116: Terminal UFCF Growth Rate
D117: Discount Rate (WACC) | E117: =L95 -> 285.48764 | F117: =+G117-0.5% -> 0.045 | G117: =+H117-0.5% -> 0.05 | H117: =+I117-0.5% -> 0.055 | I117: 0.06 | J117: =+I117+0.5% -> 0.065 | K117: =+J117+0.5% -> 0.07 | L117: =+K117+0.5% -> 0.075
E118: =+E119-0.5% -> 0.098258859 | F118: 300.15762 | G118: 327.69294 | H118: 361.5935 | I118: 404.3549 | J118: 459.97344 | K118: 535.27379 | L118: 642.94906
E119: =+E120-0.5% -> 0.10325886 | F119: 272.73815 | G119: 295.1651 | H119: 322.23928 | I119: 355.57211 | J119: 397.61738 | K119: 452.30447 | L119: 526.34377
E120: =+E121-0.5% -> 0.10825886 | F120: 249.65603 | G120: 268.22292 | H120: 290.27598 | I120: 316.89878 | J120: 349.67588 | K120: 391.02017 | L120: 444.79552
E121: 0.11325886 | F121: 229.95807 | G121: 245.54188 | H121: 263.80061 | I121: 285.48764 | J121: 311.66856 | K121: 343.90164 | L121: 384.55972
E122: =+E121+0.5% -> 0.11825886 | F122: 212.95131 | G122: 226.18554 | H122: 241.51184 | I122: 259.46886 | J122: 280.79754 | K122: 306.54586 | L122: 338.24632
E123: =+E122+0.5% -> 0.12325886 | F123: 198.11987 | G123: 209.47312 | H123: 222.48964 | I123: 237.56381 | J123: 255.22543 | K123: 276.20323 | L123: 301.52797
E124: =+E123+0.5% -> 0.12825886 | F124: 185.07181 | G124: 194.89783 | H124: 206.06514 | I124: 218.86846 | J124: 233.69575 | K124: 251.0681 | L124: 271.70233

Sheet WACC Build
C2: ="WACC Build For "&D5 -> WACC Build For TopBuild Corp.
C3: $ in thousands except per share | J3: Values
C5: Company Name | D5: ='Revenue Build & Growth Drivers'!D5 -> TopBuild Corp. | G5: Basic Shares Outstanding | J5: =+'Integrated DCF Model'!D66 -> 31775.877
C6: Ticker | D6: ='Revenue Build & Growth Drivers'!D6 -> BLD | G6: Fully Diluted Shares Outstanding | J6: =+'Integrated DCF Model'!D71 -> 32100.077
C7: Valuation Date | D7: ='Revenue Build & Growth Drivers'!D7 -> 45394
C8: Latest Adj. Closing Share Price Date | D8: ='Revenue Build & Growth Drivers'!D8 -> 45393
C9: Latest Adj. Closing Share Price | D9: ='Revenue Build & Growth Drivers'!D9 -> 421.45
C11: Cost of Debt Calculation | F11: Beta (β) Calculator
C14: Total Interest Expenses | D14: =+'Financial Statement Model'!F21 -> 74614 | F14: =D5&" ("&D6&")" -> TopBuild Corp. (BLD) | J14: S&P 500 Index
F15: Date | G15: Adj. Close Price | H15: Return (%) | J15: Date | K15: Adj. Close Price | L15: Return (%)
C16: Short-term Bank Credit/Revolver | D16: =+IFERROR(AVERAGE('Financial Statement Model'!E271:F271),0) -> 0 | F16: 44287 | G16: 222.38 | J16: 44287 | K16: 4181.17
C17: Current Portion of LT Debt & Finance leases | D17: =+IFERROR(AVERAGE('Financial Statement Model'!E258:F258),0)+IFERROR(AVERAGE('Financial Statement Model'!E297:F297),0) -> 45615.5 | F17: 44317 | G17: 198.05 | H17: =+G17/G16-1 -> -0.10940732 | J17: 44317 | K17: 4204.11 | L17: =+K17/K16-1 -> 0.0054865026
C18: LT Debt & Finance leases (Ex. Current Portion) | D18: =+IFERROR(AVERAGE('Financial Statement Model'!E259:F259),0)+IFERROR(AVERAGE('Financial Statement Model'!E300:F300),0) -> 1400554 | F18: 44348 | G18: 197.78 | H18: =+G18/G17-1 -> -0.0013632921 | J18: 44348 | K18: 4297.5 | L18: =+K18/K17-1 -> 0.022213976
C19: Total Debt | D19: =SUM(D16:D18) -> 1446169.5 | F19: 44378 | G19: 202.69 | H19: =+G19/G18-1 -> 0.024825564 | J19: 44378 | K19: 4395.26 | L19: =+K19/K18-1 -> 0.022748109
F20: 44409 | G20: 218.79 | H20: =+G20/G19-1 -> 0.079431644 | J20: 44409 | K20: 4522.68 | L20: =+K20/K19-1 -> 0.028990321
C21: Pre-tax Cost of Debt | D21: =+IFERROR(D14/D19,0) -> 0.051594229 | F21: 44440 | G21: 204.81 | H21: =+G21/G20-1 -> -0.063896887 | J21: 44440 | K21: 4307.54 | L21: =+K21/K20-1 -> -0.04756914
C22: Effective Tax Rate | D22: =+IF('Financial Statement Model'!F41<0,AVERAGEIFS('Financial Statement Model'!D41:F41,'Financial Statement Model'!D41:F41,">0"),'Financial Statement Model'!F41) -> 0.25588534 | F22: 44470 | G22: 256.97 | H22: =+G22/G21-1 -> 0.25467506 | J22: 44470 | K22: 4605.38 | L22: =+K22/K21-1 -> 0.069143873
F23: 44501 | G23: 269.79 | H23: =+G23/G22-1 -> 0.049889092 | J23: 44501 | K23: 4567 | L23: =+K23/K22-1 -> -0.0083337314
C24: Effective Cost of Debt | D24: =+D21*(1-D22) -> 0.038392022 | F24: 44531 | G24: 275.91 | H24: =+G24/G23-1 -> 0.02268431 | J24: 44531 | K24: 4766.18 | L24: =+K24/K23-1 -> 0.043612875
F25: 44562 | G25: 232.65 | H25: =+G25/G24-1 -> -0.15679026 | J25: 44562 | K25: 4515.55 | L25: =+K25/K24-1 -> -0.052585089
C26: Cost of Equity Calculation | F26: 44593 | G26: 214.68 | H26: =+G26/G25-1 -> -0.07724049 | J26: 44593 | K26: 4373.94 | L26: =+K26/K25-1 -> -0.031360521
F27: 44621 | G27: 181.39 | H27: =+G27/G26-1 -> -0.15506801 | J27: 44621 | K27: 4530.41 | L27: =+K27/K26-1 -> 0.035773239
F28: 44652 | G28: 181.14 | H28: =+G28/G27-1 -> -0.0013782458 | J28: 44652 | K28: 4131.93 | L28: =+K28/K27-1 -> -0.087956719
C29: Equity Risk Premium | D29: 0.0413 | F29: 44682 | G29: 197.26 | H29: =+G29/G28-1 -> 0.08899194 | J29: 44682 | K29: 4132.15 | L29: =+K29/K28-1 -> 5.3243884e-05
C30: Risk-free Rate | D30: 0.0456 | F30: 44713 | G30: 167.16 | H30: =+G30/G29-1 -> -0.15259049 | J30: 44713 | K30: 3785.38 | L30: =+K30/K29-1 -> -0.083919993
C31: Company Beta | D31: =+L52 -> 1.8293233 | F31: 44743 | G31: 211.72 | H31: =+G31/G30-1 -> 0.26657095 | J31: 44743 | K31: 4130.29 | L31: =+K31/K30-1 -> 0.091116348
F32: 44774 | G32: 183.76 | H32: =+G32/G31-1 -> -0.13206121 | J32: 44774 | K32: 3955 | L32: =+K32/K31-1 -> -0.042440119
C33: Cost of Equity | D33: =+D30+D31*D29 -> 0.12115105 | F33: 44805 | G33: 164.78 | H33: =+G33/G32-1 -> -0.1032869 | J33: 44805 | K33: 3585.62 | L33: =+K33/K32-1 -> -0.093395702
F34: 44835 | G34: 170.14 | H34: =+G34/G33-1 -> 0.032528219 | J34: 44835 | K34: 3871.98 | L34: =+K34/K33-1 -> 0.079863455
C35: Capital Structure and WACC | F35: 44866 | G35: 154.08 | H35: =+G35/G34-1 -> -0.094392853 | J35: 44866 | K35: 4080.11 | L35: =+K35/K34-1 -> 0.05375286
F36: 44896 | G36: 156.49 | H36: =+G36/G35-1 -> 0.015641225 | J36: 44896 | K36: 3839.5 | L36: =+K36/K35-1 -> -0.058971449
F37: 44927 | G37: 200.06 | H37: =+G37/G36-1 -> 0.27842035 | J37: 44927 | K37: 4076.6 | L37: =+K37/K36-1 -> 0.061752832
C38: Total Debt | D38: =+'Financial Statement Model'!F258+'Financial Statement Model'!F259+'Financial Statement Model'!F271+'Financial Statement Model'!F297+'Financial Statement Model'!F300 -> 1426134 | F38: 44958 | G38: 207.59 | H38: =+G38/G37-1 -> 0.037638708 | J38: 44958 | K38: 3970.15 | L38: =+K38/K37-1 -> -0.026112447
C39: % of Total Capital | D39: =+D38/(D38+D40) -> 0.095363525 | F39: 44986 | G39: 208.14 | H39: =+G39/G38-1 -> 0.0026494532 | J39: 44986 | K39: 4109.31 | L39: =+K39/K38-1 -> 0.035051572
C40: Equity Value | D40: =+D9*J6 -> 13528577 | F40: 45017 | G40: 225.48 | H40: =+G40/G39-1 -> 0.083309311 | J40: 45017 | K40: 4169.48 | L40: =+K40/K39-1 -> 0.014642361
C41: % of Total Capital | D41: =+D40/(D38+D40) -> 0.90463647 | F41: 45047 | G41: 201.66 | H41: =+G41/G40-1 -> -0.1056413 | J41: 45047 | K41: 4179.83 | L41: =+K41/K40-1 -> 0.0024823239
F42: 45078 | G42: 266.02 | H42: =+G42/G41-1 -> 0.31915105 | J42: 45078 | K42: 4450.38 | L42: =+K42/K41-1 -> 0.064727513
C43: Weighted Average Cost of Capital (WACC) | D43: =D39*D24+D41*D33 -> 0.11325886 | F43: 45108 | G43: 273.93 | H43: =+G43/G42-1 -> 0.029734606 | J43: 45108 | K43: 4588.96 | L43: =+K43/K42-1 -> 0.031138914
F44: 45139 | G44: 290.08 | H44: =+G44/G43-1 -> 0.058956668 | J44: 45139 | K44: 4507.66 | L44: =+K44/K43-1 -> -0.017716432
F45: 45170 | G45: 251.6 | H45: =+G45/G44-1 -> -0.13265306 | J45: 45170 | K45: 4288.05 | L45: =+K45/K44-1 -> -0.048719291
F46: 45200 | G46: 228.76 | H46: =+G46/G45-1 -> -0.090779014 | J46: 45200 | K46: 4193.8 | L46: =+K46/K45-1 -> -0.021979688
F47: 45231 | G47: 295.78 | H47: =+G47/G46-1 -> 0.2929708 | J47: 45231 | K47: 4567.8 | L47: =+K47/K46-1 -> 0.089179265
F48: 45261 | G48: 374.26 | H48: =+G48/G47-1 -> 0.26533234 | J48: 45261 | K48: 4769.83 | L48: =+K48/K47-1 -> 0.044229169
F49: 45292 | G49: 369.13 | H49: =+G49/G48-1 -> -0.013707049 | J49: 45292 | K49: 4845.65 | L49: =+K49/K48-1 -> 0.015895745
F50: 45323 | G50: 402.38 | H50: =+G50/G49-1 -> 0.090076667 | J50: 45323 | K50: 5096.27 | L50: =+K50/K49-1 -> 0.051720615
F51: 45352 | G51: 440.73 | H51: =+G51/G50-1 -> 0.095307918 | J51: 45352 | K51: 5254.35 | L51: =+K51/K50-1 -> 0.031018765
K52: Company Beta (3Y Monthly) >> | L52: =+SLOPE(H17:H51,L17:L51) -> 1.8293233
